{
    "config": {
        "allow_infeasible": true,
        "bvns_max_k": 10,
        "bvns_min_k": 7,
        "construction": "nearestNeighbor",
        "first_improve": true,
        "local_search": "PVND",
        "metaheuristic": "BVNS",
        "num_threads": 1,
        "operators": [
            "centExchange_1",
            "centExchange_2",
            "centExchange_3",
            "centExchange_5",
            "moveAll_2",
            "moveAll_10",
            "relocate_1",
            "relocate_2",
            "relocate_3",
            "relocate_4",
            "relocate_5",
            "exchangeIds",
            "exchange_1_2",
            "exchange_2_4",
            "exchange_3_4",
            "revExchange_1_2",
            "revExchange_2_2",
            "revExchange_3_3",
            "revExchange_3_4",
            "revExchange_4_4"
        ],
        "perturbation": [
            "randomMoveAll"
        ],
        "stop_on_feasible": false,
        "timeout": 520
    },
    "histogram": {
        "all": {
            "centExchange_1": 8747,
            "centExchange_2": 5620,
            "centExchange_3": 4049,
            "centExchange_5": 2990,
            "exchangeIds": 3510,
            "exchange_1_2": 2537,
            "exchange_2_4": 2127,
            "exchange_3_4": 2093,
            "moveAll_10": 13634,
            "moveAll_2": 9526,
            "relocate_1": 7335,
            "relocate_2": 4481,
            "relocate_3": 3013,
            "relocate_4": 2631,
            "relocate_5": 2433,
            "revExchange_1_2": 2632,
            "revExchange_2_2": 2250,
            "revExchange_3_3": 2184,
            "revExchange_3_4": 1962,
            "revExchange_4_4": 1934
        },
        "improving": {
            "centExchange_1": 5988,
            "centExchange_2": 2863,
            "centExchange_3": 1294,
            "centExchange_5": 236,
            "exchangeIds": 1434,
            "exchange_1_2": 492,
            "exchange_2_4": 84,
            "exchange_3_4": 53,
            "moveAll_10": 11060,
            "moveAll_2": 6812,
            "relocate_1": 4990,
            "relocate_2": 2211,
            "relocate_3": 778,
            "relocate_4": 413,
            "relocate_5": 225,
            "revExchange_1_2": 656,
            "revExchange_2_2": 307,
            "revExchange_3_3": 279,
            "revExchange_3_4": 63,
            "revExchange_4_4": 35
        },
        "rate": {
            "centExchange_1": 0.6845775842666626,
            "centExchange_2": 0.5094305872917175,
            "centExchange_3": 0.31958508491516113,
            "centExchange_5": 0.07892976701259613,
            "exchangeIds": 0.4085470139980316,
            "exchange_1_2": 0.19392983615398407,
            "exchange_2_4": 0.03949224203824997,
            "exchange_3_4": 0.025322504341602325,
            "moveAll_10": 0.8112072944641113,
            "moveAll_2": 0.7150955200195313,
            "relocate_1": 0.6802999377250671,
            "relocate_2": 0.4934166371822357,
            "relocate_3": 0.25821441411972046,
            "relocate_4": 0.15697453916072845,
            "relocate_5": 0.0924784243106842,
            "revExchange_1_2": 0.24924011528491974,
            "revExchange_2_2": 0.13644444942474365,
            "revExchange_3_3": 0.12774725258350372,
            "revExchange_3_4": 0.03211009129881859,
            "revExchange_4_4": 0.018097206950187683
        }
    },
    "last_improvement": 464,
    "name": "berlin52-13.2-1",
    "solution": {
        "fitness": 19642,
        "is_feasible": true,
        "permutation": [
            36,
            23,
            31,
            43,
            15,
            46,
            13,
            51,
            12,
            11,
            5,
            37,
            35,
            17,
            41,
            29,
            28,
            22,
            30,
            9,
            8,
            7,
            0,
            45,
            19,
            6,
            1,
            16,
            34,
            38,
            21,
            40,
            39,
            32,
            47,
            26,
            48,
            2,
            18,
            49,
            10,
            3,
            20,
            4,
            42,
            27,
            25,
            24,
            44,
            33,
            14,
            50
        ],
        "permutation_orig_ids": [
            "37",
            "24",
            "32",
            "44",
            "16",
            "47",
            "14",
            "52",
            "13",
            "12",
            "6",
            "38",
            "36",
            "18",
            "42",
            "30",
            "29",
            "23",
            "31",
            "10",
            "9",
            "8",
            "1",
            "46",
            "20",
            "7",
            "2",
            "17",
            "35",
            "39",
            "22",
            "41",
            "40",
            "33",
            "48",
            "27",
            "49",
            "3",
            "19",
            "50",
            "11",
            "4",
            "21",
            "5",
            "43",
            "28",
            "26",
            "25",
            "45",
            "34",
            "15",
            "51"
        ]
    },
    "steps": {
        "0": 1022117,
        "145": 21476,
        "147": 21345,
        "29": 1021955,
        "42": 1021123,
        "444": 20705,
        "445": 20288,
        "446": 20012,
        "454": 19764,
        "464": 19642,
        "54": 1020753,
        "57": 22147,
        "58": 21705,
        "84": 21523
    },
    "timeout": 520
}