{
    "config": {
        "allow_infeasible": true,
        "bvns_max_k": 10,
        "bvns_min_k": 7,
        "construction": "nearestNeighbor",
        "first_improve": true,
        "local_search": "PVND",
        "metaheuristic": "BVNS",
        "num_threads": 1,
        "operators": [
            "centExchange_1",
            "centExchange_2",
            "centExchange_3",
            "centExchange_5",
            "moveAll_2",
            "moveAll_10",
            "relocate_1",
            "relocate_2",
            "relocate_3",
            "relocate_4",
            "relocate_5",
            "exchangeIds",
            "exchange_1_2",
            "exchange_2_4",
            "exchange_3_4",
            "revExchange_1_2",
            "revExchange_2_2",
            "revExchange_3_3",
            "revExchange_3_4",
            "revExchange_4_4"
        ],
        "perturbation": [
            "randomMoveAll"
        ],
        "stop_on_feasible": false,
        "timeout": 520
    },
    "histogram": {
        "all": {
            "centExchange_1": 7591,
            "centExchange_2": 4802,
            "centExchange_3": 3571,
            "centExchange_5": 2757,
            "exchangeIds": 2825,
            "exchange_1_2": 2064,
            "exchange_2_4": 1824,
            "exchange_3_4": 1786,
            "moveAll_10": 12124,
            "moveAll_2": 8587,
            "relocate_1": 5864,
            "relocate_2": 3577,
            "relocate_3": 2632,
            "relocate_4": 2237,
            "relocate_5": 2066,
            "revExchange_1_2": 2139,
            "revExchange_2_2": 1829,
            "revExchange_3_3": 1790,
            "revExchange_3_4": 1639,
            "revExchange_4_4": 1626
        },
        "improving": {
            "centExchange_1": 5116,
            "centExchange_2": 2327,
            "centExchange_3": 1096,
            "centExchange_5": 282,
            "exchangeIds": 1048,
            "exchange_1_2": 315,
            "exchange_2_4": 80,
            "exchange_3_4": 46,
            "moveAll_10": 9805,
            "moveAll_2": 6155,
            "relocate_1": 3762,
            "relocate_2": 1548,
            "relocate_3": 670,
            "relocate_4": 303,
            "relocate_5": 144,
            "revExchange_1_2": 458,
            "revExchange_2_2": 168,
            "revExchange_3_3": 177,
            "revExchange_3_4": 29,
            "revExchange_4_4": 19
        },
        "rate": {
            "centExchange_1": 0.6739559769630432,
            "centExchange_2": 0.48458975553512573,
            "centExchange_3": 0.30691683292388916,
            "centExchange_5": 0.10228509455919266,
            "exchangeIds": 0.3709734380245209,
            "exchange_1_2": 0.15261627733707428,
            "exchange_2_4": 0.04385964944958687,
            "exchange_3_4": 0.025755878537893295,
            "moveAll_10": 0.8087264895439148,
            "moveAll_2": 0.7167811989784241,
            "relocate_1": 0.641541600227356,
            "relocate_2": 0.4327648878097534,
            "relocate_3": 0.2545592784881592,
            "relocate_4": 0.13544926047325134,
            "relocate_5": 0.06969990581274033,
            "revExchange_1_2": 0.21411874890327454,
            "revExchange_2_2": 0.09185346961021423,
            "revExchange_3_3": 0.09888268262147903,
            "revExchange_3_4": 0.017693715170025826,
            "revExchange_4_4": 0.011685117147862911
        }
    },
    "last_improvement": 60,
    "name": "berlin52-10.4-1",
    "solution": {
        "fitness": 2023360,
        "is_feasible": false,
        "permutation": [
            20,
            22,
            29,
            28,
            37,
            47,
            23,
            27,
            13,
            12,
            10,
            24,
            34,
            33,
            38,
            35,
            7,
            0,
            36,
            50,
            11,
            26,
            44,
            21,
            51,
            3,
            43,
            45,
            19,
            31,
            8,
            6,
            4,
            42,
            40,
            49,
            1,
            25,
            5,
            41,
            46,
            48,
            2,
            18,
            17,
            14,
            16,
            39,
            32,
            30,
            9,
            15
        ],
        "permutation_orig_ids": [
            "21",
            "23",
            "30",
            "29",
            "38",
            "48",
            "24",
            "28",
            "14",
            "13",
            "11",
            "25",
            "35",
            "34",
            "39",
            "36",
            "8",
            "1",
            "37",
            "51",
            "12",
            "27",
            "45",
            "22",
            "52",
            "4",
            "44",
            "46",
            "20",
            "32",
            "9",
            "7",
            "5",
            "43",
            "41",
            "50",
            "2",
            "26",
            "6",
            "42",
            "47",
            "49",
            "3",
            "19",
            "18",
            "15",
            "17",
            "40",
            "33",
            "31",
            "10",
            "16"
        ]
    },
    "steps": {
        "0": 3024769,
        "21": 3023359,
        "27": 3022505,
        "3": 3024106,
        "37": 3022333,
        "49": 3021816,
        "50": 2023910,
        "59": 2023564,
        "60": 2023360,
        "9": 3023753
    },
    "timeout": 520
}