{
    "config": {
        "allow_infeasible": true,
        "bvns_max_k": 10,
        "bvns_min_k": 7,
        "construction": "nearestNeighbor",
        "first_improve": true,
        "local_search": "PVND",
        "metaheuristic": "BVNS",
        "num_threads": 1,
        "operators": [
            "centExchange_1",
            "centExchange_2",
            "centExchange_3",
            "centExchange_5",
            "moveAll_2",
            "moveAll_10",
            "relocate_1",
            "relocate_2",
            "relocate_3",
            "relocate_4",
            "relocate_5",
            "exchangeIds",
            "exchange_1_2",
            "exchange_2_4",
            "exchange_3_4",
            "revExchange_1_2",
            "revExchange_2_2",
            "revExchange_3_3",
            "revExchange_3_4",
            "revExchange_4_4"
        ],
        "perturbation": [
            "randomMoveAll"
        ],
        "stop_on_feasible": false,
        "timeout": 10840
    },
    "histogram": {
        "all": {
            "centExchange_1": 397,
            "centExchange_2": 279,
            "centExchange_3": 190,
            "centExchange_5": 255,
            "exchangeIds": 1,
            "exchange_1_2": 1,
            "exchange_2_4": 1,
            "exchange_3_4": 1,
            "moveAll_10": 441,
            "moveAll_2": 284,
            "relocate_1": 451,
            "relocate_2": 1,
            "relocate_3": 1,
            "relocate_4": 1,
            "relocate_5": 1,
            "revExchange_1_2": 1,
            "revExchange_2_2": 1,
            "revExchange_3_3": 1,
            "revExchange_3_4": 1,
            "revExchange_4_4": 1
        },
        "improving": {
            "centExchange_1": 395,
            "centExchange_2": 277,
            "centExchange_3": 188,
            "centExchange_5": 253,
            "exchangeIds": 0,
            "exchange_1_2": 0,
            "exchange_2_4": 0,
            "exchange_3_4": 0,
            "moveAll_10": 439,
            "moveAll_2": 282,
            "relocate_1": 450,
            "relocate_2": 0,
            "relocate_3": 0,
            "relocate_4": 0,
            "relocate_5": 0,
            "revExchange_1_2": 0,
            "revExchange_2_2": 0,
            "revExchange_3_3": 0,
            "revExchange_3_4": 0,
            "revExchange_4_4": 0
        },
        "rate": {
            "centExchange_1": 0.994962215423584,
            "centExchange_2": 0.9928315281867981,
            "centExchange_3": 0.9894737005233765,
            "centExchange_5": 0.9921568632125854,
            "exchangeIds": 0.0,
            "exchange_1_2": 0.0,
            "exchange_2_4": 0.0,
            "exchange_3_4": 0.0,
            "moveAll_10": 0.9954648613929749,
            "moveAll_2": 0.9929577708244324,
            "relocate_1": 0.9977827072143555,
            "relocate_2": 0.0,
            "relocate_3": 0.0,
            "relocate_4": 0.0,
            "relocate_5": 0.0,
            "revExchange_1_2": 0.0,
            "revExchange_2_2": 0.0,
            "revExchange_3_3": 0.0,
            "revExchange_3_4": 0.0,
            "revExchange_4_4": 0.0
        }
    },
    "last_improvement": 10831,
    "name": "vm1084-1084-840.00-0",
    "solution": {
        "fitness": 2625134,
        "is_feasible": true,
        "permutation": [
            755,
            784,
            917,
            843,
            973,
            974,
            1061,
            872,
            859,
            666,
            187,
            181,
            676,
            653,
            77,
            305,
            884,
            891,
            828,
            1025,
            1002,
            689,
            1007,
            788,
            722,
            904,
            965,
            961,
            699,
            980,
            930,
            819,
            816,
            658,
            824,
            955,
            1051,
            777,
            1081,
            897,
            949,
            986,
            1048,
            702,
            615,
            605,
            611,
            934,
            732,
            1057,
            663,
            1082,
            792,
            739,
            873,
            920,
            1071,
            1073,
            887,
            798,
            964,
            778,
            865,
            921,
            488,
            209,
            367,
            889,
            291,
            199,
            137,
            278,
            333,
            234,
            432,
            517,
            170,
            372,
            606,
            1064,
            957,
            770,
            879,
            999,
            681,
            941,
            943,
            1049,
            782,
            963,
            970,
            750,
            802,
            842,
            794,
            793,
            672,
            837,
            289,
            915,
            39,
            962,
            416,
            671,
            114,
            417,
            598,
            454,
            93,
            823,
            177,
            696,
            890,
            533,
            122,
            576,
            649,
            691,
            312,
            56,
            608,
            588,
            110,
            112,
            226,
            640,
            425,
            841,
            292,
            858,
            14,
            763,
            550,
            11,
            749,
            313,
            492,
            470,
            625,
            347,
            502,
            883,
            395,
            46,
            363,
            559,
            90,
            913,
            409,
            65,
            769,
            1028,
            880,
            906,
            781,
            720,
            940,
            687,
            729,
            1015,
            572,
            455,
            1072,
            296,
            273,
            337,
            622,
            389,
            888,
            270,
            392,
            342,
            27,
            94,
            506,
            1067,
            91,
            245,
            376,
            836,
            790,
            978,
            496,
            359,
            365,
            149,
            84,
            38,
            266,
            741,
            677,
            426,
            766,
            527,
            706,
            939,
            633,
            240,
            261,
            89,
            123,
            96,
            353,
            797,
            1017,
            263,
            57,
            0,
            583,
            427,
            7,
            893,
            1043,
            180,
            1027,
            24,
            332,
            738,
            866,
            184,
            193,
            773,
            767,
            450,
            260,
            253,
            420,
            352,
            634,
            355,
            1001,
            34,
            531,
            627,
            556,
            51,
            573,
            457,
            19,
            232,
            220,
            40,
            165,
            366,
            335,
            285,
            233,
            265,
            848,
            22,
            317,
            407,
            1070,
            867,
            277,
            992,
            256,
            757,
            532,
            152,
            650,
            63,
            396,
            564,
            567,
            815,
            523,
            931,
            775,
            966,
            660,
            929,
            907,
            863,
            662,
            1042,
            847,
            956,
            1054,
            958,
            834,
            942,
            595,
            228,
            553,
            4,
            144,
            586,
            1063,
            731,
            733,
            1053,
            125,
            140,
            85,
            219,
            345,
            302,
            324,
            391,
            196,
            81,
            213,
            593,
            102,
            178,
            98,
            612,
            948,
            877,
            394,
            641,
            236,
            443,
            293,
            587,
            521,
            66,
            174,
            173,
            385,
            882,
            536,
            535,
            215,
            565,
            364,
            566,
            591,
            74,
            371,
            853,
            717,
            700,
            346,
            609,
            910,
            844,
            831,
            1076,
            667,
            86,
            339,
            23,
            146,
            189,
            227,
            471,
            509,
            522,
            388,
            6,
            614,
            946,
            97,
            436,
            511,
            638,
            665,
            791,
            160,
            398,
            401,
            525,
            871,
            916,
            806,
            221,
            318,
            656,
            1058,
            952,
            155,
            52,
            539,
            72,
            579,
            370,
            597,
            518,
            1045,
            115,
            519,
            528,
            348,
            951,
            894,
            1035,
            118,
            8,
            26,
            495,
            190,
            206,
            838,
            762,
            744,
            134,
            645,
            304,
            390,
            10,
            686,
            712,
            839,
            868,
            21,
            516,
            497,
            32,
            200,
            214,
            561,
            707,
            239,
            418,
            463,
            477,
            157,
            334,
            133,
            30,
            130,
            845,
            881,
            581,
            244,
            503,
            55,
            988,
            991,
            602,
            490,
            159,
            639,
            1046,
            670,
            1014,
            827,
            248,
            501,
            172,
            624,
            113,
            585,
            982,
            69,
            541,
            498,
            513,
            383,
            632,
            578,
            415,
            445,
            476,
            596,
            875,
            489,
            164,
            132,
            229,
            747,
            478,
            326,
            977,
            945,
            779,
            1030,
            737,
            885,
            607,
            76,
            247,
            510,
            92,
            719,
            983,
            772,
            979,
            818,
            981,
            817,
            985,
            659,
            950,
            446,
            751,
            551,
            310,
            49,
            563,
            251,
            327,
            129,
            1060,
            83,
            131,
            288,
            128,
            424,
            230,
            325,
            976,
            1059,
            724,
            440,
            472,
            938,
            179,
            171,
            604,
            176,
            124,
            216,
            411,
            554,
            854,
            726,
            692,
            898,
            821,
            515,
            223,
            301,
            644,
            400,
            549,
            208,
            473,
            224,
            79,
            203,
            259,
            785,
            547,
            680,
            902,
            61,
            250,
            995,
            121,
            119,
            142,
            20,
            175,
            508,
            654,
            75,
            505,
            512,
            560,
            412,
            500,
            768,
            846,
            805,
            600,
            760,
            279,
            648,
            166,
            1075,
            13,
            284,
            286,
            876,
            101,
            655,
            960,
            765,
            437,
            413,
            438,
            947,
            730,
            429,
            212,
            330,
            462,
            678,
            984,
            708,
            698,
            756,
            307,
            568,
            693,
            1006,
            1016,
            238,
            154,
            78,
            727,
            1033,
            369,
            295,
            461,
            716,
            637,
            968,
            746,
            786,
            343,
            138,
            908,
            932,
            969,
            735,
            728,
            589,
            451,
            64,
            514,
            50,
            201,
            54,
            252,
            453,
            257,
            928,
            814,
            309,
            542,
            852,
            704,
            264,
            1078,
            465,
            1055,
            800,
            204,
            9,
            211,
            491,
            482,
            933,
            900,
            126,
            191,
            474,
            243,
            1079,
            255,
            249,
            104,
            1062,
            830,
            857,
            870,
            281,
            799,
            759,
            997,
            998,
            524,
            357,
            636,
            601,
            613,
            16,
            136,
            646,
            850,
            268,
            378,
            323,
            148,
            319,
            393,
            764,
            1012,
            12,
            647,
            360,
            269,
            657,
            467,
            225,
            1026,
            42,
            43,
            272,
            444,
            103,
            351,
            959,
            1032,
            306,
            544,
            1021,
            308,
            569,
            202,
            117,
            743,
            714,
            338,
            37,
            235,
            856,
            710,
            552,
            464,
            618,
            99,
            901,
            701,
            903,
            703,
            825,
            1031,
            758,
            736,
            62,
            820,
            1044,
            603,
            1052,
            918,
            494,
            107,
            80,
            860,
            487,
            410,
            575,
            47,
            534,
            558,
            629,
            254,
            520,
            145,
            139,
            675,
            484,
            300,
            789,
            267,
            316,
            280,
            163,
            745,
            162,
            141,
            195,
            276,
            423,
            967,
            924,
            829,
            1056,
            923,
            1005,
            88,
            1,
            183,
            404,
            143,
            328,
            620,
            399,
            150,
            740,
            685,
            135,
            290,
            18,
            862,
            428,
            734,
            111,
            109,
            105,
            447,
            421,
            507,
            374,
            577,
            242,
            899,
            341,
            282,
            610,
            1066,
            73,
            106,
            108,
            120,
            754,
            892,
            158,
            493,
            349,
            1000,
            822,
            435,
            537,
            562,
            555,
            182,
            25,
            925,
            787,
            156,
            543,
            1023,
            1010,
            896,
            59,
            167,
            386,
            721,
            584,
            456,
            297,
            458,
            3,
            434,
            439,
            362,
            695,
            29,
            621,
            643,
            283,
            832,
            1013,
            406,
            53,
            33,
            1050,
            197,
            194,
            783,
            635,
            776,
            835,
            833,
            237,
            100,
            466,
            210,
            336,
            217,
            358,
            761,
            331,
            298,
            626,
            188,
            468,
            1036,
            972,
            935,
            294,
            481,
            483,
            570,
            905,
            271,
            911,
            673,
            886,
            954,
            574,
            95,
            480,
            874,
            15,
            809,
            715,
            804,
            688,
            826,
            912,
            1009,
            1019,
            45,
            373,
            1040,
            694,
            241,
            599,
            448,
            849,
            623,
            379,
            774,
            161,
            361,
            207,
            919,
            895,
            67,
            397,
            652,
            1068,
            989,
            697,
            71,
            580,
            368,
            987,
            878,
            936,
            642,
            41,
            485,
            479,
            723,
            274,
            192,
            442,
            381,
            1020,
            1018,
            504,
            592,
            1069,
            529,
            1039,
            937,
            526,
            684,
            590,
            616,
            169,
            546,
            70,
            58,
            582,
            387,
            725,
            186,
            682,
            68,
            651,
            246,
            674,
            795,
            994,
            1065,
            1004,
            630,
            486,
            322,
            198,
            810,
            405,
            218,
            231,
            222,
            801,
            748,
            993,
            864,
            668,
            548,
            851,
            402,
            17,
            953,
            31,
            354,
            151,
            813,
            433,
            990,
            557,
            538,
            530,
            540,
            153,
            262,
            87,
            350,
            258,
            460,
            571,
            594,
            996,
            356,
            808,
            36,
            431,
            82,
            669,
            315,
            44,
            459,
            375,
            384,
            718,
            926,
            168,
            1038,
            752,
            661,
            975,
            441,
            1008,
            922,
            545,
            311,
            380,
            147,
            1077,
            971,
            807,
            742,
            944,
            803,
            909,
            780,
            1047,
            753,
            382,
            449,
            205,
            377,
            1074,
            914,
            664,
            709,
            35,
            628,
            1011,
            116,
            430,
            299,
            303,
            861,
            811,
            329,
            344,
            403,
            683,
            812,
            690,
            1080,
            475,
            631,
            771,
            60,
            499,
            2,
            414,
            679,
            796,
            1003,
            1022,
            1024,
            408,
            1034,
            617,
            5,
            419,
            452,
            127,
            340,
            287,
            320,
            469,
            185,
            869,
            1029,
            927,
            422,
            1041,
            48,
            855,
            705,
            1037,
            711,
            28,
            314,
            275,
            321,
            619,
            840,
            713,
            1083
        ],
        "permutation_orig_ids": [
            "756",
            "785",
            "918",
            "844",
            "974",
            "975",
            "1062",
            "873",
            "860",
            "667",
            "188",
            "182",
            "677",
            "654",
            "78",
            "306",
            "885",
            "892",
            "829",
            "1026",
            "1003",
            "690",
            "1008",
            "789",
            "723",
            "905",
            "966",
            "962",
            "700",
            "981",
            "931",
            "820",
            "817",
            "659",
            "825",
            "956",
            "1052",
            "778",
            "1082",
            "898",
            "950",
            "987",
            "1049",
            "703",
            "616",
            "606",
            "612",
            "935",
            "733",
            "1058",
            "664",
            "1083",
            "793",
            "740",
            "874",
            "921",
            "1072",
            "1074",
            "888",
            "799",
            "965",
            "779",
            "866",
            "922",
            "489",
            "210",
            "368",
            "890",
            "292",
            "200",
            "138",
            "279",
            "334",
            "235",
            "433",
            "518",
            "171",
            "373",
            "607",
            "1065",
            "958",
            "771",
            "880",
            "1000",
            "682",
            "942",
            "944",
            "1050",
            "783",
            "964",
            "971",
            "751",
            "803",
            "843",
            "795",
            "794",
            "673",
            "838",
            "290",
            "916",
            "40",
            "963",
            "417",
            "672",
            "115",
            "418",
            "599",
            "455",
            "94",
            "824",
            "178",
            "697",
            "891",
            "534",
            "123",
            "577",
            "650",
            "692",
            "313",
            "57",
            "609",
            "589",
            "111",
            "113",
            "227",
            "641",
            "426",
            "842",
            "293",
            "859",
            "15",
            "764",
            "551",
            "12",
            "750",
            "314",
            "493",
            "471",
            "626",
            "348",
            "503",
            "884",
            "396",
            "47",
            "364",
            "560",
            "91",
            "914",
            "410",
            "66",
            "770",
            "1029",
            "881",
            "907",
            "782",
            "721",
            "941",
            "688",
            "730",
            "1016",
            "573",
            "456",
            "1073",
            "297",
            "274",
            "338",
            "623",
            "390",
            "889",
            "271",
            "393",
            "343",
            "28",
            "95",
            "507",
            "1068",
            "92",
            "246",
            "377",
            "837",
            "791",
            "979",
            "497",
            "360",
            "366",
            "150",
            "85",
            "39",
            "267",
            "742",
            "678",
            "427",
            "767",
            "528",
            "707",
            "940",
            "634",
            "241",
            "262",
            "90",
            "124",
            "97",
            "354",
            "798",
            "1018",
            "264",
            "58",
            "1",
            "584",
            "428",
            "8",
            "894",
            "1044",
            "181",
            "1028",
            "25",
            "333",
            "739",
            "867",
            "185",
            "194",
            "774",
            "768",
            "451",
            "261",
            "254",
            "421",
            "353",
            "635",
            "356",
            "1002",
            "35",
            "532",
            "628",
            "557",
            "52",
            "574",
            "458",
            "20",
            "233",
            "221",
            "41",
            "166",
            "367",
            "336",
            "286",
            "234",
            "266",
            "849",
            "23",
            "318",
            "408",
            "1071",
            "868",
            "278",
            "993",
            "257",
            "758",
            "533",
            "153",
            "651",
            "64",
            "397",
            "565",
            "568",
            "816",
            "524",
            "932",
            "776",
            "967",
            "661",
            "930",
            "908",
            "864",
            "663",
            "1043",
            "848",
            "957",
            "1055",
            "959",
            "835",
            "943",
            "596",
            "229",
            "554",
            "5",
            "145",
            "587",
            "1064",
            "732",
            "734",
            "1054",
            "126",
            "141",
            "86",
            "220",
            "346",
            "303",
            "325",
            "392",
            "197",
            "82",
            "214",
            "594",
            "103",
            "179",
            "99",
            "613",
            "949",
            "878",
            "395",
            "642",
            "237",
            "444",
            "294",
            "588",
            "522",
            "67",
            "175",
            "174",
            "386",
            "883",
            "537",
            "536",
            "216",
            "566",
            "365",
            "567",
            "592",
            "75",
            "372",
            "854",
            "718",
            "701",
            "347",
            "610",
            "911",
            "845",
            "832",
            "1077",
            "668",
            "87",
            "340",
            "24",
            "147",
            "190",
            "228",
            "472",
            "510",
            "523",
            "389",
            "7",
            "615",
            "947",
            "98",
            "437",
            "512",
            "639",
            "666",
            "792",
            "161",
            "399",
            "402",
            "526",
            "872",
            "917",
            "807",
            "222",
            "319",
            "657",
            "1059",
            "953",
            "156",
            "53",
            "540",
            "73",
            "580",
            "371",
            "598",
            "519",
            "1046",
            "116",
            "520",
            "529",
            "349",
            "952",
            "895",
            "1036",
            "119",
            "9",
            "27",
            "496",
            "191",
            "207",
            "839",
            "763",
            "745",
            "135",
            "646",
            "305",
            "391",
            "11",
            "687",
            "713",
            "840",
            "869",
            "22",
            "517",
            "498",
            "33",
            "201",
            "215",
            "562",
            "708",
            "240",
            "419",
            "464",
            "478",
            "158",
            "335",
            "134",
            "31",
            "131",
            "846",
            "882",
            "582",
            "245",
            "504",
            "56",
            "989",
            "992",
            "603",
            "491",
            "160",
            "640",
            "1047",
            "671",
            "1015",
            "828",
            "249",
            "502",
            "173",
            "625",
            "114",
            "586",
            "983",
            "70",
            "542",
            "499",
            "514",
            "384",
            "633",
            "579",
            "416",
            "446",
            "477",
            "597",
            "876",
            "490",
            "165",
            "133",
            "230",
            "748",
            "479",
            "327",
            "978",
            "946",
            "780",
            "1031",
            "738",
            "886",
            "608",
            "77",
            "248",
            "511",
            "93",
            "720",
            "984",
            "773",
            "980",
            "819",
            "982",
            "818",
            "986",
            "660",
            "951",
            "447",
            "752",
            "552",
            "311",
            "50",
            "564",
            "252",
            "328",
            "130",
            "1061",
            "84",
            "132",
            "289",
            "129",
            "425",
            "231",
            "326",
            "977",
            "1060",
            "725",
            "441",
            "473",
            "939",
            "180",
            "172",
            "605",
            "177",
            "125",
            "217",
            "412",
            "555",
            "855",
            "727",
            "693",
            "899",
            "822",
            "516",
            "224",
            "302",
            "645",
            "401",
            "550",
            "209",
            "474",
            "225",
            "80",
            "204",
            "260",
            "786",
            "548",
            "681",
            "903",
            "62",
            "251",
            "996",
            "122",
            "120",
            "143",
            "21",
            "176",
            "509",
            "655",
            "76",
            "506",
            "513",
            "561",
            "413",
            "501",
            "769",
            "847",
            "806",
            "601",
            "761",
            "280",
            "649",
            "167",
            "1076",
            "14",
            "285",
            "287",
            "877",
            "102",
            "656",
            "961",
            "766",
            "438",
            "414",
            "439",
            "948",
            "731",
            "430",
            "213",
            "331",
            "463",
            "679",
            "985",
            "709",
            "699",
            "757",
            "308",
            "569",
            "694",
            "1007",
            "1017",
            "239",
            "155",
            "79",
            "728",
            "1034",
            "370",
            "296",
            "462",
            "717",
            "638",
            "969",
            "747",
            "787",
            "344",
            "139",
            "909",
            "933",
            "970",
            "736",
            "729",
            "590",
            "452",
            "65",
            "515",
            "51",
            "202",
            "55",
            "253",
            "454",
            "258",
            "929",
            "815",
            "310",
            "543",
            "853",
            "705",
            "265",
            "1079",
            "466",
            "1056",
            "801",
            "205",
            "10",
            "212",
            "492",
            "483",
            "934",
            "901",
            "127",
            "192",
            "475",
            "244",
            "1080",
            "256",
            "250",
            "105",
            "1063",
            "831",
            "858",
            "871",
            "282",
            "800",
            "760",
            "998",
            "999",
            "525",
            "358",
            "637",
            "602",
            "614",
            "17",
            "137",
            "647",
            "851",
            "269",
            "379",
            "324",
            "149",
            "320",
            "394",
            "765",
            "1013",
            "13",
            "648",
            "361",
            "270",
            "658",
            "468",
            "226",
            "1027",
            "43",
            "44",
            "273",
            "445",
            "104",
            "352",
            "960",
            "1033",
            "307",
            "545",
            "1022",
            "309",
            "570",
            "203",
            "118",
            "744",
            "715",
            "339",
            "38",
            "236",
            "857",
            "711",
            "553",
            "465",
            "619",
            "100",
            "902",
            "702",
            "904",
            "704",
            "826",
            "1032",
            "759",
            "737",
            "63",
            "821",
            "1045",
            "604",
            "1053",
            "919",
            "495",
            "108",
            "81",
            "861",
            "488",
            "411",
            "576",
            "48",
            "535",
            "559",
            "630",
            "255",
            "521",
            "146",
            "140",
            "676",
            "485",
            "301",
            "790",
            "268",
            "317",
            "281",
            "164",
            "746",
            "163",
            "142",
            "196",
            "277",
            "424",
            "968",
            "925",
            "830",
            "1057",
            "924",
            "1006",
            "89",
            "2",
            "184",
            "405",
            "144",
            "329",
            "621",
            "400",
            "151",
            "741",
            "686",
            "136",
            "291",
            "19",
            "863",
            "429",
            "735",
            "112",
            "110",
            "106",
            "448",
            "422",
            "508",
            "375",
            "578",
            "243",
            "900",
            "342",
            "283",
            "611",
            "1067",
            "74",
            "107",
            "109",
            "121",
            "755",
            "893",
            "159",
            "494",
            "350",
            "1001",
            "823",
            "436",
            "538",
            "563",
            "556",
            "183",
            "26",
            "926",
            "788",
            "157",
            "544",
            "1024",
            "1011",
            "897",
            "60",
            "168",
            "387",
            "722",
            "585",
            "457",
            "298",
            "459",
            "4",
            "435",
            "440",
            "363",
            "696",
            "30",
            "622",
            "644",
            "284",
            "833",
            "1014",
            "407",
            "54",
            "34",
            "1051",
            "198",
            "195",
            "784",
            "636",
            "777",
            "836",
            "834",
            "238",
            "101",
            "467",
            "211",
            "337",
            "218",
            "359",
            "762",
            "332",
            "299",
            "627",
            "189",
            "469",
            "1037",
            "973",
            "936",
            "295",
            "482",
            "484",
            "571",
            "906",
            "272",
            "912",
            "674",
            "887",
            "955",
            "575",
            "96",
            "481",
            "875",
            "16",
            "810",
            "716",
            "805",
            "689",
            "827",
            "913",
            "1010",
            "1020",
            "46",
            "374",
            "1041",
            "695",
            "242",
            "600",
            "449",
            "850",
            "624",
            "380",
            "775",
            "162",
            "362",
            "208",
            "920",
            "896",
            "68",
            "398",
            "653",
            "1069",
            "990",
            "698",
            "72",
            "581",
            "369",
            "988",
            "879",
            "937",
            "643",
            "42",
            "486",
            "480",
            "724",
            "275",
            "193",
            "443",
            "382",
            "1021",
            "1019",
            "505",
            "593",
            "1070",
            "530",
            "1040",
            "938",
            "527",
            "685",
            "591",
            "617",
            "170",
            "547",
            "71",
            "59",
            "583",
            "388",
            "726",
            "187",
            "683",
            "69",
            "652",
            "247",
            "675",
            "796",
            "995",
            "1066",
            "1005",
            "631",
            "487",
            "323",
            "199",
            "811",
            "406",
            "219",
            "232",
            "223",
            "802",
            "749",
            "994",
            "865",
            "669",
            "549",
            "852",
            "403",
            "18",
            "954",
            "32",
            "355",
            "152",
            "814",
            "434",
            "991",
            "558",
            "539",
            "531",
            "541",
            "154",
            "263",
            "88",
            "351",
            "259",
            "461",
            "572",
            "595",
            "997",
            "357",
            "809",
            "37",
            "432",
            "83",
            "670",
            "316",
            "45",
            "460",
            "376",
            "385",
            "719",
            "927",
            "169",
            "1039",
            "753",
            "662",
            "976",
            "442",
            "1009",
            "923",
            "546",
            "312",
            "381",
            "148",
            "1078",
            "972",
            "808",
            "743",
            "945",
            "804",
            "910",
            "781",
            "1048",
            "754",
            "383",
            "450",
            "206",
            "378",
            "1075",
            "915",
            "665",
            "710",
            "36",
            "629",
            "1012",
            "117",
            "431",
            "300",
            "304",
            "862",
            "812",
            "330",
            "345",
            "404",
            "684",
            "813",
            "691",
            "1081",
            "476",
            "632",
            "772",
            "61",
            "500",
            "3",
            "415",
            "680",
            "797",
            "1004",
            "1023",
            "1025",
            "409",
            "1035",
            "618",
            "6",
            "420",
            "453",
            "128",
            "341",
            "288",
            "321",
            "470",
            "186",
            "870",
            "1030",
            "928",
            "423",
            "1042",
            "49",
            "856",
            "706",
            "1038",
            "712",
            "29",
            "315",
            "276",
            "322",
            "620",
            "841",
            "714",
            "1084"
        ]
    },
    "steps": {
        "0": 8493716,
        "1": 8441941,
        "10": 8223942,
        "100": 7521213,
        "1001": 4491872,
        "10013": 2670815,
        "10030": 2670677,
        "1004": 4491656,
        "10047": 2670090,
        "10064": 2669580,
        "1007": 4489662,
        "10081": 2669347,
        "101": 7510247,
        "10101": 2669324,
        "1011": 4488332,
        "10121": 2666369,
        "1014": 4486240,
        "10140": 2666226,
        "10157": 2665791,
        "10173": 2665664,
        "1018": 4484969,
        "10190": 2665603,
        "102": 7504801,
        "10207": 2664688,
        "1021": 4482744,
        "10224": 2664384,
        "1025": 4480387,
        "10263": 2664071,
        "1028": 4478363,
        "103": 7497900,
        "10300": 2664039,
        "1032": 4475476,
        "10335": 2663945,
        "1035": 4474362,
        "10369": 2663885,
        "1039": 4474291,
        "104": 7497868,
        "10401": 2663431,
        "1042": 4470148,
        "10432": 2663370,
        "1046": 4467734,
        "10461": 2663350,
        "10489": 2663312,
        "1049": 4465764,
        "105": 7496985,
        "10515": 2663222,
        "1053": 4464326,
        "10540": 2663173,
        "10563": 2663055,
        "1057": 4461627,
        "10584": 2663003,
        "106": 7484685,
        "1060": 4458241,
        "10604": 2662849,
        "10623": 2662596,
        "1064": 4456059,
        "10640": 2655091,
        "10657": 2652107,
        "10674": 2651139,
        "1068": 4452607,
        "1069": 4450474,
        "10691": 2646789,
        "107": 7484629,
        "1071": 4450434,
        "10714": 2645253,
        "10737": 2644933,
        "1075": 4449607,
        "10758": 2644102,
        "10778": 2643910,
        "1078": 4449576,
        "10797": 2643399,
        "108": 7481287,
        "10814": 2626082,
        "1082": 4446511,
        "10831": 2625134,
        "1085": 4446173,
        "1089": 4442546,
        "109": 7475091,
        "1093": 4440178,
        "1097": 4439989,
        "11": 8219194,
        "110": 7457161,
        "1101": 4437507,
        "1104": 4437050,
        "1107": 4437041,
        "111": 7456662,
        "1111": 4433747,
        "1115": 4432531,
        "112": 7455334,
        "1120": 4429651,
        "1124": 4428907,
        "1128": 4428820,
        "113": 7450724,
        "1132": 4427118,
        "1136": 4419052,
        "114": 7444736,
        "1140": 4418092,
        "1144": 4417506,
        "1148": 4415354,
        "115": 7429679,
        "1152": 4414350,
        "1157": 4414220,
        "116": 7429188,
        "1161": 4414170,
        "1165": 4409043,
        "1169": 4407812,
        "117": 7425440,
        "1173": 4406457,
        "1177": 4405608,
        "118": 7425296,
        "1182": 4405422,
        "1184": 4403238,
        "1188": 4400744,
        "119": 7424131,
        "1192": 4399080,
        "1197": 4394839,
        "12": 8201726,
        "120": 7420365,
        "1201": 4392808,
        "1204": 4392800,
        "1208": 4382941,
        "121": 7418161,
        "1213": 4380887,
        "1217": 4376953,
        "1219": 4376362,
        "122": 7414492,
        "1220": 4370920,
        "1225": 4368695,
        "123": 7412408,
        "1230": 4367437,
        "1234": 4367117,
        "1239": 4363542,
        "124": 7408163,
        "1241": 4363153,
        "1246": 4363061,
        "125": 7401484,
        "1251": 4355787,
        "1256": 4354155,
        "1258": 4350031,
        "126": 7386668,
        "1263": 4347994,
        "1265": 4347215,
        "1267": 4345726,
        "127": 7386495,
        "1272": 4344510,
        "1277": 4342836,
        "1278": 4342214,
        "128": 7376197,
        "1283": 4342173,
        "1285": 4337807,
        "129": 7355926,
        "1291": 4336163,
        "1296": 4336162,
        "13": 8185417,
        "130": 7355105,
        "1301": 4333805,
        "1305": 4333797,
        "131": 7348527,
        "1310": 4331244,
        "1314": 4326424,
        "1319": 4322713,
        "132": 7347553,
        "1320": 4319358,
        "1321": 4318364,
        "1326": 4318333,
        "133": 7346968,
        "1331": 4318322,
        "1336": 4318174,
        "1337": 4314858,
        "134": 7343765,
        "1343": 4314397,
        "1349": 4313236,
        "135": 7338388,
        "1355": 4312961,
        "1358": 4312700,
        "136": 7338369,
        "1364": 4311202,
        "1365": 4303313,
        "1366": 4299252,
        "1367": 4298297,
        "1368": 4297496,
        "1369": 4295227,
        "137": 7337692,
        "1370": 4295141,
        "1371": 4289814,
        "1372": 4284190,
        "1373": 4284046,
        "1374": 4282751,
        "1375": 4276218,
        "1376": 4265635,
        "1377": 4261403,
        "1379": 4257456,
        "138": 7336522,
        "1380": 4255957,
        "1382": 4253765,
        "1383": 4253758,
        "1386": 4253697,
        "1388": 4251570,
        "139": 7332975,
        "1390": 4249801,
        "1393": 4248002,
        "1395": 4247620,
        "1398": 4242343,
        "1399": 4242302,
        "14": 8168838,
        "140": 7332371,
        "1403": 4241330,
        "1406": 4240996,
        "1409": 4231896,
        "141": 7322826,
        "1413": 4229139,
        "1417": 4229032,
        "142": 7322707,
        "1420": 4228268,
        "1424": 4227589,
        "1428": 4226476,
        "143": 7322275,
        "1432": 4225397,
        "1436": 4225272,
        "144": 7318999,
        "1440": 4221296,
        "1441": 4218773,
        "1443": 4217626,
        "1447": 4216763,
        "145": 7312265,
        "1451": 4215757,
        "1456": 4212130,
        "146": 7304631,
        "1461": 4210349,
        "1467": 4208186,
        "147": 7299454,
        "1472": 4194224,
        "1478": 4191823,
        "148": 7290916,
        "1483": 4191295,
        "1489": 4190511,
        "149": 7290197,
        "1495": 4190029,
        "15": 8163139,
        "150": 7274005,
        "1501": 4188300,
        "1507": 4187989,
        "151": 7273942,
        "1513": 4186148,
        "1518": 4186146,
        "152": 7273240,
        "1524": 4184420,
        "153": 7272846,
        "1531": 4183842,
        "1537": 4183480,
        "154": 7270377,
        "1544": 4182148,
        "155": 7265251,
        "1550": 4181976,
        "1557": 4181500,
        "1559": 4181122,
        "156": 7258755,
        "1565": 4179672,
        "157": 7253366,
        "1572": 4177456,
        "1579": 4177333,
        "158": 7250635,
        "1585": 4173565,
        "159": 7239620,
        "1592": 4170090,
        "1597": 4169649,
        "16": 8153763,
        "160": 7239433,
        "1600": 4169512,
        "1606": 4169145,
        "161": 7234891,
        "1612": 4167326,
        "1619": 4162479,
        "162": 7234851,
        "1626": 4160065,
        "163": 7231905,
        "1633": 4159661,
        "164": 7228444,
        "1641": 4157640,
        "1646": 4157512,
        "1647": 4157309,
        "1655": 4157280,
        "166": 7219988,
        "1662": 4156887,
        "167": 7212374,
        "1670": 4154460,
        "1675": 4148085,
        "168": 7207276,
        "1682": 4147419,
        "169": 7206984,
        "1690": 4145081,
        "1691": 4144076,
        "1697": 4143948,
        "17": 8125750,
        "170": 7201400,
        "1705": 4136602,
        "1713": 4124653,
        "172": 7193883,
        "1721": 4119822,
        "1728": 4118431,
        "173": 7192212,
        "1736": 4118291,
        "174": 7178316,
        "1741": 4118269,
        "1749": 4114922,
        "175": 7161850,
        "1758": 4113459,
        "1766": 4112666,
        "177": 7159604,
        "1774": 4105416,
        "178": 7146409,
        "1783": 4101240,
        "179": 7142509,
        "1792": 4094222,
        "18": 8110331,
        "180": 7138996,
        "1801": 4092707,
        "1809": 4091378,
        "1818": 4090936,
        "182": 7128085,
        "1827": 4088311,
        "183": 7124156,
        "1832": 4087264,
        "1837": 4085252,
        "184": 7112489,
        "1846": 4078130,
        "1855": 4077242,
        "186": 7107092,
        "1864": 4076879,
        "187": 7101078,
        "1873": 4074480,
        "188": 7100012,
        "1883": 4072347,
        "1889": 4071951,
        "1899": 4068674,
        "19": 8109531,
        "190": 7095088,
        "1908": 4067830,
        "191": 7086244,
        "1918": 4067399,
        "192": 7079261,
        "1928": 4067031,
        "1938": 4064839,
        "194": 7078755,
        "1948": 4063833,
        "195": 7069868,
        "1953": 4061580,
        "1959": 4060642,
        "1969": 4060046,
        "197": 7059372,
        "1979": 4058868,
        "198": 7055571,
        "1989": 4057204,
        "1995": 4056854,
        "2": 8405180,
        "20": 8103296,
        "200": 7052510,
        "2005": 4051709,
        "2007": 4050530,
        "201": 7050937,
        "2017": 4048549,
        "202": 7050834,
        "2028": 4044280,
        "2038": 4040834,
        "204": 7047948,
        "2049": 4033297,
        "205": 7047465,
        "2060": 4029526,
        "2067": 4029089,
        "207": 7033273,
        "2077": 4028522,
        "208": 7033261,
        "2088": 4028385,
        "2099": 4026381,
        "21": 8101516,
        "210": 7003768,
        "2107": 4024881,
        "211": 6981627,
        "2118": 4021297,
        "212": 6964822,
        "2125": 4020970,
        "213": 6949963,
        "2136": 4020054,
        "214": 6938670,
        "2147": 4014601,
        "215": 6932035,
        "2159": 4012232,
        "216": 6920575,
        "2163": 4012165,
        "217": 6909814,
        "2174": 4011086,
        "218": 6900686,
        "2186": 4010620,
        "219": 6896266,
        "2198": 4008606,
        "22": 8096734,
        "220": 6870603,
        "2208": 4003842,
        "221": 6865901,
        "2217": 4003521,
        "222": 6852039,
        "2227": 4002532,
        "223": 6849356,
        "2234": 4001092,
        "224": 6842365,
        "2243": 4001085,
        "225": 6837681,
        "2255": 3996664,
        "226": 6837343,
        "2267": 3996559,
        "227": 6829899,
        "2279": 3994417,
        "228": 6822156,
        "2284": 3994049,
        "229": 6820395,
        "2297": 3993019,
        "2299": 3992930,
        "23": 8091370,
        "230": 6806699,
        "231": 6792335,
        "2311": 3992841,
        "2315": 3991263,
        "232": 6786135,
        "2327": 3991208,
        "233": 6777238,
        "234": 6767343,
        "2340": 3991040,
        "235": 6764608,
        "2353": 3990809,
        "236": 6756683,
        "2360": 3989674,
        "237": 6752309,
        "2372": 3988256,
        "238": 6751728,
        "2385": 3986281,
        "239": 6749895,
        "2397": 3985037,
        "24": 8077948,
        "240": 6747176,
        "2403": 3983255,
        "241": 6746457,
        "2417": 3983114,
        "242": 6745777,
        "243": 6738242,
        "2430": 3982546,
        "244": 6738085,
        "2443": 3970025,
        "245": 6733333,
        "2457": 3969323,
        "246": 6729193,
        "2469": 3966558,
        "247": 6729025,
        "248": 6721530,
        "2483": 3966386,
        "2488": 3964689,
        "249": 6719962,
        "2495": 3964647,
        "25": 8059905,
        "250": 6718074,
        "2508": 3961659,
        "251": 6695704,
        "252": 6695066,
        "2522": 3954483,
        "253": 6694391,
        "2536": 3954275,
        "254": 6693571,
        "2544": 3952034,
        "255": 6691480,
        "2552": 3951986,
        "256": 6690536,
        "2561": 3950394,
        "2566": 3935101,
        "257": 6690015,
        "2577": 3933023,
        "258": 6688843,
        "2580": 3932327,
        "259": 6680700,
        "2594": 3925678,
        "2599": 3923551,
        "26": 8058872,
        "260": 6680260,
        "2606": 3923180,
        "261": 6676604,
        "262": 6675639,
        "2620": 3919108,
        "263": 6669617,
        "2632": 3916839,
        "264": 6664766,
        "2647": 3905468,
        "265": 6664690,
        "266": 6653576,
        "2661": 3904732,
        "2668": 3900312,
        "267": 6647524,
        "268": 6646812,
        "2682": 3898913,
        "269": 6644371,
        "2697": 3898832,
        "2698": 3898306,
        "27": 8057409,
        "270": 6643933,
        "2700": 3898235,
        "2707": 3897471,
        "271": 6640105,
        "2717": 3896316,
        "2718": 3895316,
        "272": 6637958,
        "2721": 3894237,
        "2722": 3893711,
        "273": 6635200,
        "2737": 3892204,
        "274": 6631507,
        "2742": 3891333,
        "2747": 3890244,
        "275": 6628093,
        "276": 6628061,
        "2762": 3887872,
        "2769": 3886910,
        "277": 6623579,
        "278": 6612597,
        "2784": 3886871,
        "279": 6612333,
        "2798": 3885504,
        "28": 8052083,
        "280": 6606671,
        "2803": 3885484,
        "281": 6605215,
        "2818": 3885376,
        "282": 6593617,
        "283": 6590337,
        "2833": 3876949,
        "284": 6590223,
        "2844": 3871462,
        "285": 6588707,
        "2851": 3870661,
        "2859": 3862020,
        "286": 6587813,
        "2866": 3860279,
        "287": 6586295,
        "288": 6579639,
        "2882": 3860268,
        "289": 6571937,
        "2897": 3859431,
        "29": 8039700,
        "290": 6559139,
        "291": 6556057,
        "2912": 3852280,
        "292": 6546116,
        "2928": 3851405,
        "293": 6542401,
        "294": 6540739,
        "2944": 3850167,
        "295": 6540732,
        "296": 6539561,
        "2960": 3843023,
        "297": 6539406,
        "2976": 3835133,
        "298": 6539296,
        "2982": 3835073,
        "299": 6532652,
        "2998": 3832308,
        "3": 8369061,
        "30": 8039549,
        "300": 6530144,
        "3001": 3830291,
        "301": 6520694,
        "3017": 3825955,
        "302": 6520145,
        "3027": 3822219,
        "303": 6517588,
        "3035": 3821104,
        "304": 6517212,
        "305": 6514737,
        "3052": 3820344,
        "306": 6511564,
        "3068": 3820287,
        "307": 6510777,
        "308": 6507327,
        "3085": 3819878,
        "309": 6504625,
        "31": 8017839,
        "310": 6493556,
        "3102": 3814722,
        "311": 6492076,
        "312": 6486199,
        "3120": 3806017,
        "313": 6485526,
        "3137": 3804151,
        "314": 6480115,
        "315": 6470699,
        "3155": 3800547,
        "316": 6465297,
        "3173": 3798696,
        "318": 6454890,
        "319": 6453043,
        "3192": 3798388,
        "3193": 3797821,
        "3196": 3797073,
        "32": 8016418,
        "320": 6451313,
        "3200": 3794761,
        "3202": 3791055,
        "3204": 3790233,
        "321": 6440460,
        "3219": 3790200,
        "322": 6437108,
        "323": 6437092,
        "3236": 3789300,
        "324": 6431030,
        "325": 6418034,
        "3255": 3781560,
        "326": 6417783,
        "3273": 3775332,
        "328": 6415652,
        "3288": 3774349,
        "329": 6402665,
        "33": 7988907,
        "330": 6402477,
        "3307": 3768236,
        "331": 6400845,
        "332": 6400014,
        "3324": 3767642,
        "333": 6392111,
        "3343": 3765858,
        "335": 6377087,
        "3352": 3765241,
        "3357": 3762595,
        "3359": 3762554,
        "336": 6372812,
        "3363": 3762547,
        "3367": 3761659,
        "337": 6372811,
        "338": 6372628,
        "3386": 3759141,
        "3399": 3758812,
        "34": 7987325,
        "340": 6371903,
        "341": 6369548,
        "3418": 3755473,
        "342": 6367960,
        "3437": 3750986,
        "344": 6365267,
        "345": 6339920,
        "3457": 3750794,
        "346": 6338374,
        "347": 6331063,
        "3477": 3741614,
        "349": 6330791,
        "3497": 3739867,
        "35": 7986533,
        "350": 6329062,
        "351": 6328171,
        "3517": 3736581,
        "3523": 3735325,
        "353": 6326067,
        "354": 6324721,
        "3544": 3731162,
        "355": 6324190,
        "3564": 3731094,
        "357": 6321668,
        "358": 6318220,
        "3584": 3729415,
        "359": 6318218,
        "3590": 3729369,
        "36": 7974693,
        "361": 6316613,
        "3611": 3729067,
        "362": 6316341,
        "363": 6313768,
        "3632": 3728502,
        "365": 6307524,
        "3653": 3723349,
        "366": 6304803,
        "367": 6297472,
        "3674": 3721480,
        "369": 6295981,
        "3695": 3721173,
        "37": 7956374,
        "370": 6294923,
        "371": 6293255,
        "3717": 3720229,
        "3726": 3719436,
        "373": 6292494,
        "374": 6291987,
        "3747": 3714166,
        "375": 6286719,
        "3769": 3708555,
        "377": 6286711,
        "378": 6284142,
        "3791": 3700443,
        "38": 7956017,
        "380": 6276819,
        "381": 6250548,
        "3812": 3694560,
        "383": 6244359,
        "3834": 3687415,
        "384": 6244318,
        "3853": 3686769,
        "3856": 3682674,
        "386": 6238603,
        "3864": 3682474,
        "387": 6238230,
        "3881": 3682323,
        "389": 6237270,
        "39": 7930279,
        "390": 6232997,
        "3900": 3682131,
        "392": 6232818,
        "3922": 3678127,
        "393": 6230141,
        "3944": 3677742,
        "395": 6219243,
        "3953": 3677710,
        "396": 6216379,
        "3976": 3676987,
        "398": 6213820,
        "399": 6212495,
        "3999": 3676486,
        "4": 8347889,
        "40": 7929554,
        "401": 6211777,
        "402": 6202020,
        "4021": 3675727,
        "4038": 3671344,
        "404": 6201843,
        "405": 6201611,
        "4061": 3670494,
        "407": 6194709,
        "4070": 3668983,
        "408": 6192600,
        "4093": 3664507,
        "41": 7909187,
        "410": 6192526,
        "4104": 3664463,
        "411": 6153787,
        "412": 6143506,
        "4127": 3662571,
        "413": 6105622,
        "4133": 3660752,
        "4137": 3660146,
        "414": 6099119,
        "4143": 3659767,
        "415": 6089814,
        "416": 6082362,
        "4166": 3659003,
        "417": 6079881,
        "418": 6066201,
        "4189": 3650580,
        "419": 6060365,
        "4192": 3650545,
        "4195": 3650351,
        "42": 7879604,
        "420": 6054957,
        "421": 6040728,
        "4218": 3636199,
        "422": 6036307,
        "423": 6026499,
        "4231": 3635412,
        "424": 6023872,
        "4240": 3633048,
        "425": 6013457,
        "4252": 3632763,
        "426": 6008001,
        "427": 6001538,
        "4275": 3622711,
        "428": 6000509,
        "429": 5993656,
        "4299": 3620665,
        "43": 7872453,
        "430": 5986028,
        "431": 5985243,
        "432": 5983459,
        "4322": 3619636,
        "433": 5974558,
        "434": 5974309,
        "4343": 3619072,
        "435": 5971695,
        "436": 5971551,
        "4367": 3618487,
        "437": 5963205,
        "438": 5957219,
        "439": 5950561,
        "4391": 3617846,
        "44": 7861353,
        "440": 5949405,
        "441": 5945360,
        "4412": 3617685,
        "442": 5942661,
        "443": 5942619,
        "4435": 3617679,
        "444": 5939220,
        "445": 5939121,
        "4459": 3617507,
        "446": 5935295,
        "447": 5929967,
        "4476": 3617012,
        "448": 5929109,
        "449": 5926896,
        "4496": 3616490,
        "45": 7846353,
        "450": 5925093,
        "4508": 3616387,
        "451": 5917397,
        "452": 5916048,
        "453": 5910047,
        "4532": 3610669,
        "454": 5901360,
        "4542": 3608194,
        "455": 5895319,
        "4554": 3602736,
        "456": 5891860,
        "4567": 3602096,
        "457": 5890890,
        "4579": 3602084,
        "458": 5890462,
        "459": 5887019,
        "46": 7836120,
        "460": 5885658,
        "4603": 3597401,
        "461": 5884876,
        "462": 5871023,
        "4627": 3593746,
        "463": 5868399,
        "464": 5868170,
        "465": 5864759,
        "4651": 3592912,
        "466": 5855001,
        "467": 5854724,
        "4672": 3592898,
        "468": 5845303,
        "4684": 3591433,
        "469": 5844291,
        "47": 7832648,
        "470": 5841089,
        "4706": 3589995,
        "471": 5837751,
        "472": 5836219,
        "473": 5831663,
        "4731": 3589583,
        "474": 5824418,
        "475": 5820145,
        "4756": 3587133,
        "476": 5818703,
        "477": 5799676,
        "4777": 3586465,
        "478": 5799571,
        "479": 5798833,
        "4799": 3586029,
        "48": 7831789,
        "481": 5797596,
        "482": 5797435,
        "4824": 3585787,
        "4829": 3581995,
        "483": 5795167,
        "4838": 3575869,
        "484": 5789290,
        "485": 5789271,
        "486": 5788086,
        "4864": 3567615,
        "487": 5785583,
        "4871": 3562666,
        "489": 5783660,
        "4890": 3561283,
        "49": 7808899,
        "490": 5781079,
        "491": 5779110,
        "4916": 3560131,
        "492": 5773571,
        "494": 5768710,
        "4942": 3560110,
        "495": 5767625,
        "496": 5758304,
        "4969": 3558901,
        "497": 5755827,
        "499": 5755304,
        "4995": 3553554,
        "5": 8329891,
        "50": 7805097,
        "500": 5749197,
        "501": 5748916,
        "502": 5748167,
        "5022": 3552177,
        "504": 5745886,
        "5049": 3551025,
        "505": 5745198,
        "506": 5742043,
        "507": 5742039,
        "5076": 3550298,
        "509": 5736163,
        "5094": 3550270,
        "51": 7795313,
        "510": 5735890,
        "511": 5734991,
        "5121": 3548045,
        "5126": 3547982,
        "513": 5731679,
        "5131": 3547814,
        "514": 5729801,
        "5144": 3547424,
        "5146": 3547139,
        "515": 5728586,
        "5151": 3547112,
        "5157": 3545787,
        "517": 5727397,
        "518": 5724265,
        "5185": 3544755,
        "52": 7788997,
        "520": 5722469,
        "521": 5721298,
        "5212": 3541283,
        "522": 5721158,
        "5239": 3537469,
        "524": 5716848,
        "5249": 3537257,
        "525": 5716719,
        "5265": 3537072,
        "527": 5713314,
        "528": 5710826,
        "5292": 3536655,
        "53": 7787435,
        "530": 5703041,
        "531": 5697773,
        "532": 5695147,
        "5320": 3534607,
        "534": 5692288,
        "5348": 3531113,
        "535": 5690316,
        "537": 5688993,
        "5377": 3528825,
        "538": 5686815,
        "5391": 3528818,
        "54": 7779176,
        "540": 5682287,
        "5406": 3528490,
        "541": 5676420,
        "5421": 3528301,
        "543": 5674935,
        "544": 5673583,
        "5444": 3527259,
        "5459": 3526999,
        "546": 5656385,
        "547": 5655109,
        "5474": 3526442,
        "5488": 3526433,
        "549": 5644049,
        "55": 7777876,
        "550": 5640999,
        "5514": 3526292,
        "552": 5608536,
        "5529": 3526266,
        "553": 5604940,
        "554": 5601646,
        "555": 5594933,
        "5557": 3520964,
        "556": 5592480,
        "557": 5581726,
        "558": 5575727,
        "5586": 3512259,
        "559": 5571879,
        "5594": 3508911,
        "56": 7769075,
        "560": 5571417,
        "561": 5565744,
        "5612": 3507243,
        "562": 5563092,
        "563": 5551768,
        "5633": 3507236,
        "564": 5547918,
        "565": 5541549,
        "566": 5538289,
        "5661": 3505073,
        "567": 5533915,
        "5676": 3504890,
        "568": 5529378,
        "569": 5514651,
        "57": 7767906,
        "570": 5508685,
        "5705": 3504827,
        "571": 5498664,
        "572": 5497345,
        "573": 5492480,
        "5733": 3502273,
        "574": 5489100,
        "575": 5488644,
        "576": 5481977,
        "5762": 3495583,
        "577": 5474089,
        "5773": 3493960,
        "578": 5467878,
        "579": 5459362,
        "5797": 3493855,
        "58": 7762033,
        "580": 5457369,
        "581": 5454412,
        "582": 5446428,
        "5826": 3490969,
        "583": 5444173,
        "584": 5438888,
        "585": 5429275,
        "5855": 3483599,
        "586": 5427823,
        "587": 5426460,
        "588": 5423948,
        "5884": 3479735,
        "589": 5420446,
        "59": 7756372,
        "590": 5413109,
        "591": 5412863,
        "5913": 3475191,
        "592": 5411530,
        "5925": 3468640,
        "593": 5407928,
        "594": 5407268,
        "595": 5406739,
        "5955": 3464036,
        "596": 5403587,
        "597": 5400804,
        "598": 5394999,
        "5984": 3461347,
        "599": 5391961,
        "5997": 3455472,
        "6": 8292909,
        "60": 7753480,
        "600": 5389119,
        "601": 5379505,
        "602": 5379039,
        "6026": 3454328,
        "603": 5377756,
        "604": 5375354,
        "605": 5373948,
        "6056": 3454083,
        "606": 5368673,
        "607": 5361044,
        "6078": 3451993,
        "608": 5357872,
        "609": 5357059,
        "61": 7732638,
        "610": 5356327,
        "6108": 3451628,
        "611": 5354944,
        "6118": 3449180,
        "612": 5352970,
        "6124": 3447852,
        "613": 5352829,
        "614": 5352704,
        "615": 5352214,
        "6151": 3440445,
        "616": 5341202,
        "6164": 3440247,
        "617": 5339691,
        "618": 5338289,
        "6186": 3428464,
        "619": 5335747,
        "6197": 3428442,
        "62": 7723802,
        "620": 5328609,
        "621": 5328230,
        "6211": 3424950,
        "622": 5327579,
        "623": 5320281,
        "624": 5316779,
        "6240": 3424236,
        "625": 5312091,
        "626": 5309437,
        "627": 5307126,
        "6271": 3423552,
        "6272": 3423511,
        "6279": 3423376,
        "628": 5302123,
        "6288": 3419017,
        "629": 5298156,
        "6291": 3418106,
        "63": 7723131,
        "630": 5290082,
        "6305": 3417794,
        "631": 5286013,
        "632": 5285395,
        "633": 5279216,
        "6331": 3416415,
        "6334": 3416171,
        "634": 5278808,
        "6344": 3412454,
        "635": 5276675,
        "6356": 3412192,
        "636": 5267069,
        "637": 5264357,
        "638": 5263026,
        "6382": 3411810,
        "639": 5251152,
        "6394": 3410067,
        "6396": 3409209,
        "64": 7717268,
        "640": 5247366,
        "641": 5244618,
        "642": 5236523,
        "6426": 3408542,
        "643": 5236258,
        "644": 5235512,
        "645": 5234757,
        "6457": 3405260,
        "646": 5232094,
        "647": 5230402,
        "648": 5229979,
        "6487": 3404278,
        "649": 5227740,
        "6496": 3403137,
        "65": 7703089,
        "650": 5226886,
        "651": 5226664,
        "6517": 3402354,
        "652": 5217292,
        "6524": 3401789,
        "653": 5216193,
        "6532": 3401503,
        "654": 5210013,
        "6540": 3401168,
        "655": 5209448,
        "656": 5208114,
        "657": 5202748,
        "6571": 3399467,
        "6579": 3399465,
        "658": 5199631,
        "659": 5196059,
        "66": 7702879,
        "660": 5195139,
        "6610": 3396299,
        "662": 5193555,
        "6628": 3392494,
        "663": 5192825,
        "664": 5192047,
        "665": 5189789,
        "666": 5188654,
        "6660": 3390039,
        "6664": 3385789,
        "6667": 3381391,
        "6668": 3381292,
        "667": 5187158,
        "6670": 3379049,
        "6673": 3379001,
        "6674": 3377348,
        "6676": 3376502,
        "6679": 3376483,
        "668": 5177347,
        "6682": 3375881,
        "6684": 3375484,
        "6685": 3372570,
        "6688": 3370722,
        "669": 5175170,
        "6690": 3363680,
        "6693": 3363574,
        "6696": 3360971,
        "67": 7699662,
        "670": 5174945,
        "6701": 3360790,
        "6704": 3360617,
        "6707": 3360490,
        "6709": 3338867,
        "671": 5169561,
        "6715": 3336323,
        "672": 5163588,
        "6720": 3334327,
        "6723": 3333691,
        "6726": 3333472,
        "6729": 3324623,
        "673": 5163508,
        "6732": 3324472,
        "6734": 3323866,
        "6737": 3322027,
        "674": 5162292,
        "6740": 3322023,
        "6741": 3320376,
        "6749": 3320361,
        "675": 5160929,
        "6755": 3320350,
        "676": 5155761,
        "6760": 3320349,
        "6763": 3320348,
        "6765": 3319152,
        "6766": 3315412,
        "6768": 3308993,
        "677": 5154922,
        "6771": 3308729,
        "6772": 3308529,
        "6776": 3308445,
        "6779": 3306745,
        "678": 5154558,
        "6782": 3306717,
        "6785": 3306608,
        "6786": 3284845,
        "679": 5147837,
        "6790": 3283304,
        "6791": 3269779,
        "6793": 3267212,
        "6796": 3267166,
        "6799": 3267088,
        "68": 7690228,
        "680": 5143942,
        "6800": 3265868,
        "6804": 3265737,
        "6805": 3263156,
        "681": 5138393,
        "6819": 3262970,
        "682": 5137406,
        "683": 5135623,
        "6832": 3261946,
        "6842": 3261943,
        "685": 5135568,
        "6852": 3261938,
        "686": 5134252,
        "6860": 3261935,
        "6866": 3261934,
        "687": 5133397,
        "6872": 3261361,
        "6877": 3261360,
        "688": 5131886,
        "6880": 3261359,
        "6881": 3261357,
        "6883": 3256835,
        "6886": 3256794,
        "6889": 3256269,
        "689": 5129690,
        "6891": 3253992,
        "6892": 3253051,
        "6894": 3249940,
        "6895": 3248304,
        "69": 7689207,
        "690": 5127500,
        "6900": 3248294,
        "6905": 3247864,
        "6908": 3247830,
        "6909": 3240871,
        "691": 5124238,
        "6911": 3235341,
        "6914": 3234294,
        "6916": 3228623,
        "6919": 3227261,
        "692": 5121837,
        "6922": 3227246,
        "6925": 3227038,
        "6926": 3215100,
        "693": 5118330,
        "6930": 3213048,
        "6933": 3212916,
        "6936": 3212898,
        "6939": 3211043,
        "694": 5113248,
        "6940": 3205641,
        "6942": 3205525,
        "6944": 3200761,
        "6947": 3200676,
        "6950": 3200171,
        "6951": 3197279,
        "6954": 3197156,
        "6958": 3197113,
        "6959": 3194264,
        "696": 5113215,
        "6962": 3193625,
        "6964": 3191133,
        "6965": 3183757,
        "6968": 3183239,
        "697": 5111508,
        "6972": 3183122,
        "6978": 3182799,
        "698": 5111029,
        "6982": 3182792,
        "6987": 3176596,
        "699": 5109160,
        "6990": 3173048,
        "6992": 3159975,
        "6993": 3159968,
        "6995": 3158506,
        "6997": 3157240,
        "6998": 3156880,
        "7": 8286931,
        "70": 7683538,
        "700": 5104217,
        "7003": 3156872,
        "7006": 3156871,
        "7009": 3156870,
        "701": 5104172,
        "7011": 3153498,
        "7012": 3153128,
        "7017": 3152901,
        "702": 5100819,
        "7020": 3152887,
        "7021": 3152471,
        "7025": 3151405,
        "7028": 3150255,
        "7029": 3147898,
        "7031": 3143866,
        "7032": 3140542,
        "7034": 3139525,
        "7035": 3139414,
        "7037": 3135797,
        "7039": 3135666,
        "704": 5100815,
        "7040": 3135490,
        "7043": 3135403,
        "7045": 3127311,
        "7048": 3127131,
        "7049": 3117190,
        "705": 5099428,
        "7053": 3116932,
        "7054": 3109590,
        "7056": 3107233,
        "7057": 3097884,
        "706": 5097846,
        "7060": 3093018,
        "7063": 3092449,
        "7065": 3089710,
        "7068": 3089571,
        "707": 5097795,
        "7070": 3088901,
        "7073": 3088132,
        "7074": 3086038,
        "7076": 3084590,
        "7079": 3082847,
        "708": 5093681,
        "7081": 3082184,
        "7082": 3082127,
        "7085": 3082125,
        "709": 5092543,
        "7091": 3081479,
        "7096": 3081298,
        "7099": 3077368,
        "71": 7665023,
        "710": 5092510,
        "7102": 3077045,
        "7105": 3076276,
        "7107": 3069109,
        "7109": 3068405,
        "7112": 3068382,
        "7115": 3068357,
        "7116": 3044572,
        "7118": 3039594,
        "712": 5091434,
        "7121": 3036050,
        "7123": 3034011,
        "7124": 3033528,
        "7127": 3033227,
        "7129": 3029168,
        "713": 5091381,
        "7130": 3029045,
        "7134": 3025732,
        "7137": 3025628,
        "7138": 3024228,
        "714": 5087719,
        "7141": 3023298,
        "7143": 3023254,
        "7148": 3023201,
        "715": 5084893,
        "7152": 3020143,
        "7155": 3020118,
        "7158": 3018856,
        "716": 5079663,
        "7162": 3018413,
        "7163": 3008910,
        "718": 5078857,
        "7182": 3008724,
        "719": 5078122,
        "7199": 3008704,
        "72": 7663532,
        "720": 5074521,
        "7214": 3008465,
        "722": 5061200,
        "7228": 3008441,
        "723": 5060801,
        "724": 5060353,
        "7241": 3008299,
        "7252": 3008296,
        "726": 5059185,
        "7261": 3008289,
        "7269": 3008247,
        "727": 5058735,
        "7275": 3008220,
        "728": 5056543,
        "7280": 3008216,
        "7283": 3008214,
        "7286": 3007726,
        "7287": 2993830,
        "7291": 2993641,
        "7292": 2982809,
        "7295": 2982786,
        "7298": 2982678,
        "73": 7642119,
        "730": 5056058,
        "7300": 2982634,
        "7301": 2976373,
        "7306": 2976350,
        "7309": 2976257,
        "731": 5050777,
        "7312": 2976252,
        "7314": 2975542,
        "7315": 2975280,
        "732": 5030175,
        "7333": 2974742,
        "734": 5029691,
        "7348": 2973440,
        "735": 5023977,
        "736": 5011688,
        "7362": 2973408,
        "7375": 2973310,
        "738": 5009864,
        "7385": 2973295,
        "739": 5007236,
        "7395": 2973290,
        "74": 7641409,
        "7403": 2973108,
        "7409": 2973091,
        "741": 5002968,
        "7413": 2972995,
        "7416": 2972990,
        "7418": 2968954,
        "742": 5000214,
        "7423": 2968645,
        "7426": 2968640,
        "7429": 2967179,
        "743": 4997757,
        "7431": 2955203,
        "7432": 2944025,
        "7434": 2942395,
        "7446": 2942251,
        "745": 4997105,
        "7457": 2942245,
        "746": 4983634,
        "7466": 2942232,
        "7474": 2942231,
        "748": 4978573,
        "7482": 2940545,
        "7488": 2940300,
        "749": 4975189,
        "7493": 2939713,
        "7496": 2939212,
        "7499": 2939137,
        "75": 7623882,
        "7502": 2938003,
        "7504": 2934311,
        "7505": 2933733,
        "7507": 2929728,
        "751": 4972818,
        "7510": 2929365,
        "7511": 2919496,
        "752": 4967209,
        "7521": 2919495,
        "7529": 2919489,
        "7535": 2919488,
        "7539": 2919485,
        "754": 4957541,
        "7544": 2918400,
        "7547": 2918399,
        "755": 4955239,
        "7550": 2916220,
        "7553": 2916214,
        "7555": 2916213,
        "7558": 2915647,
        "7561": 2915255,
        "7564": 2914594,
        "7567": 2914498,
        "757": 4954001,
        "7571": 2912629,
        "7572": 2904629,
        "7574": 2904399,
        "7575": 2903395,
        "7577": 2897347,
        "7578": 2892399,
        "758": 4949101,
        "7580": 2890479,
        "7583": 2890044,
        "7586": 2889548,
        "7588": 2889132,
        "759": 4924270,
        "7597": 2889095,
        "76": 7621168,
        "760": 4908956,
        "7605": 2887967,
        "761": 4883521,
        "7611": 2887875,
        "7616": 2887427,
        "7619": 2887408,
        "762": 4881902,
        "7622": 2882145,
        "7625": 2881920,
        "7628": 2881916,
        "763": 4873011,
        "7630": 2875572,
        "7631": 2874448,
        "7634": 2874441,
        "7638": 2873945,
        "764": 4869516,
        "7641": 2873925,
        "7644": 2873587,
        "7645": 2865252,
        "765": 4868459,
        "7655": 2865246,
        "766": 4859749,
        "7662": 2865234,
        "7669": 2865197,
        "767": 4853501,
        "7673": 2865194,
        "7676": 2865192,
        "768": 4850909,
        "7680": 2864289,
        "7683": 2864209,
        "7686": 2860480,
        "7689": 2859263,
        "769": 4845881,
        "7690": 2858315,
        "7692": 2858289,
        "7694": 2858202,
        "7695": 2856955,
        "77": 7618226,
        "770": 4836898,
        "771": 4830314,
        "7715": 2856902,
        "772": 4829219,
        "773": 4827806,
        "7734": 2856461,
        "774": 4820680,
        "775": 4819625,
        "7751": 2856394,
        "776": 4816331,
        "7767": 2856372,
        "777": 4814750,
        "778": 4814514,
        "7781": 2856015,
        "779": 4808139,
        "7793": 2855944,
        "78": 7606976,
        "780": 4806969,
        "7804": 2855717,
        "781": 4793326,
        "7813": 2855261,
        "782": 4789505,
        "7821": 2855210,
        "7827": 2855069,
        "783": 4787611,
        "7832": 2855051,
        "7835": 2855001,
        "7837": 2842802,
        "784": 4779891,
        "7840": 2842520,
        "7843": 2842456,
        "7844": 2830064,
        "7846": 2828675,
        "7849": 2828077,
        "785": 4772126,
        "7851": 2823361,
        "786": 4767132,
        "7862": 2823316,
        "787": 4764651,
        "7877": 2821151,
        "788": 4762124,
        "789": 4757180,
        "7891": 2819083,
        "79": 7603236,
        "790": 4755137,
        "7905": 2818808,
        "791": 4744370,
        "7919": 2809497,
        "792": 4744350,
        "793": 4736858,
        "7933": 2807899,
        "794": 4733432,
        "7947": 2802825,
        "795": 4732550,
        "796": 4730720,
        "7961": 2802812,
        "797": 4729335,
        "798": 4726367,
        "799": 4725862,
        "7998": 2802123,
        "8": 8271536,
        "80": 7599062,
        "800": 4724931,
        "801": 4721135,
        "802": 4720967,
        "803": 4715230,
        "8034": 2801975,
        "805": 4713218,
        "806": 4712432,
        "8068": 2801947,
        "807": 4711753,
        "808": 4708820,
        "809": 4708163,
        "81": 7598907,
        "8101": 2801703,
        "811": 4707605,
        "812": 4707579,
        "813": 4700328,
        "8132": 2801658,
        "814": 4698666,
        "816": 4695844,
        "8162": 2801653,
        "817": 4693929,
        "818": 4693662,
        "819": 4686367,
        "8190": 2801645,
        "82": 7597041,
        "820": 4685776,
        "8216": 2801629,
        "822": 4683332,
        "823": 4681723,
        "824": 4679469,
        "8241": 2801583,
        "826": 4677646,
        "8264": 2801580,
        "827": 4677518,
        "8286": 2801577,
        "829": 4676344,
        "83": 7596439,
        "830": 4673281,
        "8306": 2801552,
        "832": 4668734,
        "8325": 2801551,
        "833": 4668225,
        "8342": 2801532,
        "835": 4657868,
        "8358": 2801530,
        "836": 4656392,
        "8372": 2801424,
        "838": 4655016,
        "8386": 2800970,
        "84": 7587896,
        "840": 4649206,
        "8400": 2798526,
        "841": 4649005,
        "8414": 2798405,
        "8428": 2798221,
        "843": 4648566,
        "8442": 2797549,
        "845": 4648244,
        "8456": 2797182,
        "847": 4640755,
        "8470": 2797060,
        "8484": 2796145,
        "849": 4636969,
        "8498": 2795841,
        "85": 7587210,
        "851": 4636045,
        "8512": 2793658,
        "852": 4635347,
        "8526": 2792813,
        "854": 4628592,
        "8540": 2792572,
        "8554": 2791490,
        "856": 4628474,
        "8568": 2791430,
        "858": 4627786,
        "8582": 2791250,
        "8596": 2790175,
        "86": 7570886,
        "860": 4627066,
        "8610": 2790056,
        "862": 4617971,
        "8624": 2789877,
        "8638": 2788867,
        "864": 4617247,
        "866": 4610299,
        "8662": 2788860,
        "868": 4609530,
        "8687": 2788847,
        "87": 7570546,
        "870": 4609377,
        "8711": 2788846,
        "872": 4609271,
        "8732": 2788839,
        "874": 4603549,
        "8765": 2787177,
        "877": 4599722,
        "879": 4594183,
        "8796": 2786475,
        "88": 7565831,
        "881": 4588992,
        "8826": 2784647,
        "883": 4585260,
        "885": 4580587,
        "8854": 2784230,
        "888": 4579732,
        "8880": 2784159,
        "89": 7554771,
        "890": 4577738,
        "8905": 2784158,
        "892": 4575051,
        "893": 4574833,
        "8930": 2779419,
        "8955": 2779163,
        "896": 4574705,
        "898": 4573505,
        "8980": 2778524,
        "9": 8243372,
        "90": 7554660,
        "9005": 2776604,
        "901": 4572728,
        "9029": 2776028,
        "904": 4569360,
        "9054": 2773212,
        "906": 4566723,
        "9079": 2772316,
        "909": 4562175,
        "91": 7552284,
        "9102": 2771420,
        "911": 4558611,
        "9130": 2770844,
        "914": 4556498,
        "9158": 2770662,
        "917": 4549705,
        "9184": 2770581,
        "919": 4548829,
        "92": 7552233,
        "9209": 2770534,
        "922": 4542026,
        "9232": 2770527,
        "925": 4541548,
        "9253": 2770464,
        "9273": 2770463,
        "928": 4538948,
        "9292": 2770462,
        "93": 7550013,
        "9309": 2770461,
        "931": 4538378,
        "9324": 2770459,
        "9338": 2759682,
        "934": 4534245,
        "9352": 2752485,
        "9366": 2746598,
        "937": 4533737,
        "9380": 2742923,
        "9393": 2742880,
        "94": 7549129,
        "940": 4533696,
        "9409": 2742749,
        "9424": 2742576,
        "943": 4533267,
        "9440": 2742095,
        "9455": 2740383,
        "946": 4530360,
        "9470": 2733115,
        "9486": 2729003,
        "949": 4527290,
        "95": 7545050,
        "950": 4527261,
        "9501": 2728957,
        "9516": 2728829,
        "953": 4523384,
        "9532": 2727984,
        "9549": 2727888,
        "956": 4523149,
        "9564": 2727778,
        "9580": 2727611,
        "959": 4520450,
        "9595": 2727182,
        "96": 7542198,
        "960": 4517836,
        "9610": 2726510,
        "9626": 2726326,
        "963": 4516368,
        "964": 4516347,
        "9641": 2721822,
        "965": 4514932,
        "9656": 2704508,
        "9672": 2704060,
        "968": 4514318,
        "9687": 2703996,
        "97": 7535426,
        "970": 4514222,
        "9703": 2703420,
        "9718": 2702844,
        "973": 4514212,
        "9733": 2702780,
        "9749": 2698077,
        "976": 4508217,
        "9764": 2692999,
        "9780": 2685486,
        "979": 4507451,
        "9795": 2678369,
        "98": 7524692,
        "981": 4506474,
        "9810": 2678356,
        "9826": 2674826,
        "984": 4504692,
        "9841": 2674660,
        "9858": 2673978,
        "987": 4500837,
        "9878": 2672634,
        "988": 4499586,
        "9896": 2672378,
        "99": 7522657,
        "991": 4494087,
        "9913": 2671674,
        "9936": 2671335,
        "994": 4493959,
        "9958": 2671145,
        "9978": 2671120,
        "998": 4492355,
        "9996": 2671062
    },
    "timeout": 10840
}