{
    "config": {
        "allow_infeasible": true,
        "bvns_max_k": 10,
        "bvns_min_k": 7,
        "construction": "nearestNeighbor",
        "first_improve": true,
        "local_search": "PVND",
        "metaheuristic": "BVNS",
        "num_threads": 8,
        "operators": [
            "centExchange_1",
            "centExchange_2",
            "centExchange_3",
            "centExchange_5",
            "moveAll_2",
            "moveAll_10",
            "relocate_1",
            "relocate_2",
            "relocate_3",
            "relocate_4",
            "relocate_5",
            "exchangeIds",
            "exchange_1_2",
            "exchange_2_4",
            "exchange_3_4",
            "revExchange_1_2",
            "revExchange_2_2",
            "revExchange_3_3",
            "revExchange_3_4",
            "revExchange_4_4"
        ],
        "perturbation": [
            "randomMoveAll"
        ],
        "stop_on_feasible": false,
        "timeout": 4170
    },
    "histogram": {
        "all": {
            "centExchange_1": 38,
            "centExchange_2": 55,
            "centExchange_3": 29,
            "centExchange_5": 27,
            "exchangeIds": 146,
            "exchange_1_2": 44,
            "exchange_2_4": 6,
            "exchange_3_4": 5,
            "moveAll_10": 89,
            "moveAll_2": 57,
            "relocate_1": 740,
            "relocate_2": 82,
            "relocate_3": 51,
            "relocate_4": 25,
            "relocate_5": 18,
            "revExchange_1_2": 26,
            "revExchange_2_2": 8,
            "revExchange_3_3": 13,
            "revExchange_3_4": 6,
            "revExchange_4_4": 6
        },
        "improving": {
            "centExchange_1": 34,
            "centExchange_2": 51,
            "centExchange_3": 25,
            "centExchange_5": 23,
            "exchangeIds": 143,
            "exchange_1_2": 41,
            "exchange_2_4": 3,
            "exchange_3_4": 2,
            "moveAll_10": 85,
            "moveAll_2": 53,
            "relocate_1": 737,
            "relocate_2": 79,
            "relocate_3": 48,
            "relocate_4": 22,
            "relocate_5": 15,
            "revExchange_1_2": 23,
            "revExchange_2_2": 5,
            "revExchange_3_3": 10,
            "revExchange_3_4": 3,
            "revExchange_4_4": 3
        },
        "rate": {
            "centExchange_1": 0.8947368264198303,
            "centExchange_2": 0.9272727370262146,
            "centExchange_3": 0.8620689511299133,
            "centExchange_5": 0.8518518805503845,
            "exchangeIds": 0.9794520735740662,
            "exchange_1_2": 0.9318181872367859,
            "exchange_2_4": 0.5,
            "exchange_3_4": 0.4000000059604645,
            "moveAll_10": 0.9550561904907227,
            "moveAll_2": 0.9298245906829834,
            "relocate_1": 0.995945930480957,
            "relocate_2": 0.9634146094322205,
            "relocate_3": 0.9411764740943909,
            "relocate_4": 0.8799999952316284,
            "relocate_5": 0.8333333134651184,
            "revExchange_1_2": 0.8846153616905212,
            "revExchange_2_2": 0.625,
            "revExchange_3_3": 0.7692307829856873,
            "revExchange_3_4": 0.5,
            "revExchange_4_4": 0.5
        }
    },
    "last_improvement": 4165,
    "name": "fl417-160.6-1",
    "solution": {
        "fitness": 117203,
        "is_feasible": true,
        "permutation": [
            250,
            256,
            260,
            286,
            264,
            288,
            292,
            270,
            296,
            272,
            293,
            269,
            291,
            266,
            287,
            265,
            263,
            279,
            252,
            396,
            385,
            395,
            393,
            223,
            221,
            239,
            210,
            206,
            227,
            367,
            365,
            61,
            57,
            43,
            38,
            149,
            151,
            348,
            308,
            334,
            324,
            325,
            338,
            178,
            337,
            181,
            183,
            161,
            187,
            165,
            166,
            168,
            170,
            193,
            175,
            199,
            176,
            200,
            40,
            49,
            54,
            56,
            282,
            284,
            262,
            283,
            259,
            78,
            63,
            55,
            52,
            34,
            134,
            110,
            109,
            131,
            114,
            113,
            137,
            139,
            117,
            119,
            123,
            145,
            122,
            124,
            147,
            125,
            127,
            4,
            6,
            9,
            24,
            33,
            48,
            50,
            75,
            79,
            91,
            96,
            247,
            243,
            220,
            219,
            86,
            76,
            66,
            73,
            85,
            196,
            174,
            173,
            171,
            172,
            194,
            190,
            164,
            162,
            184,
            160,
            182,
            313,
            312,
            311,
            310,
            21,
            31,
            23,
            30,
            27,
            20,
            3,
            11,
            8,
            152,
            126,
            148,
            120,
            142,
            138,
            116,
            32,
            297,
            319,
            322,
            129,
            130,
            300,
            339,
            327,
            301,
            342,
            344,
            346,
            347,
            302,
            330,
            305,
            106,
            133,
            112,
            115,
            121,
            141,
            118,
            140,
            144,
            128,
            28,
            29,
            14,
            51,
            62,
            215,
            238,
            230,
            202,
            390,
            362,
            357,
            400,
            401,
            228,
            232,
            211,
            216,
            241,
            245,
            224,
            412,
            370,
            369,
            377,
            411,
            372,
            236,
            207,
            229,
            226,
            208,
            209,
            203,
            204,
            391,
            407,
            361,
            389,
            381,
            363,
            392,
            366,
            104,
            88,
            89,
            246,
            248,
            242,
            240,
            212,
            234,
            235,
            233,
            213,
            90,
            94,
            253,
            378,
            249,
            398,
            275,
            261,
            255,
            257,
            281,
            295,
            268,
            278,
            376,
            415,
            386,
            374,
            397,
            414,
            413,
            410,
            84,
            87,
            39,
            156,
            179,
            177,
            317,
            353,
            333,
            46,
            69,
            65,
            111,
            136,
            394,
            371,
            103,
            101,
            70,
            74,
            68,
            399,
            359,
            388,
            102,
            0,
            12,
            19,
            25,
            15,
            163,
            159,
            157,
            169,
            195,
            155,
            318,
            352,
            314,
            180,
            326,
            335,
            2,
            18,
            7,
            42,
            45,
            276,
            244,
            406,
            379,
            349,
            1,
            135,
            343,
            299,
            341,
            307,
            105,
            332,
            99,
            277,
            285,
            271,
            267,
            273,
            383,
            222,
            336,
            356,
            16,
            36,
            10,
            13,
            150,
            53,
            298,
            323,
            167,
            154,
            143,
            146,
            95,
            360,
            358,
            364,
            405,
            92,
            188,
            35,
            316,
            355,
            351,
            59,
            368,
            237,
            402,
            404,
            225,
            201,
            231,
            309,
            153,
            191,
            198,
            197,
            37,
            80,
            47,
            254,
            251,
            100,
            409,
            387,
            71,
            329,
            258,
            280,
            375,
            186,
            189,
            185,
            158,
            26,
            5,
            382,
            214,
            83,
            77,
            44,
            274,
            294,
            289,
            58,
            67,
            331,
            304,
            41,
            82,
            373,
            290,
            403,
            192,
            17,
            350,
            81,
            72,
            218,
            60,
            93,
            64,
            306,
            328,
            345,
            315,
            205,
            384,
            217,
            354,
            408,
            22,
            107,
            108,
            321,
            303,
            132,
            320,
            340,
            380,
            97,
            98,
            416
        ],
        "permutation_orig_ids": [
            "251",
            "257",
            "261",
            "287",
            "265",
            "289",
            "293",
            "271",
            "297",
            "273",
            "294",
            "270",
            "292",
            "267",
            "288",
            "266",
            "264",
            "280",
            "253",
            "397",
            "386",
            "396",
            "394",
            "224",
            "222",
            "240",
            "211",
            "207",
            "228",
            "368",
            "366",
            "62",
            "58",
            "44",
            "39",
            "150",
            "152",
            "349",
            "309",
            "335",
            "325",
            "326",
            "339",
            "179",
            "338",
            "182",
            "184",
            "162",
            "188",
            "166",
            "167",
            "169",
            "171",
            "194",
            "176",
            "200",
            "177",
            "201",
            "41",
            "50",
            "55",
            "57",
            "283",
            "285",
            "263",
            "284",
            "260",
            "79",
            "64",
            "56",
            "53",
            "35",
            "135",
            "111",
            "110",
            "132",
            "115",
            "114",
            "138",
            "140",
            "118",
            "120",
            "124",
            "146",
            "123",
            "125",
            "148",
            "126",
            "128",
            "5",
            "7",
            "10",
            "25",
            "34",
            "49",
            "51",
            "76",
            "80",
            "92",
            "97",
            "248",
            "244",
            "221",
            "220",
            "87",
            "77",
            "67",
            "74",
            "86",
            "197",
            "175",
            "174",
            "172",
            "173",
            "195",
            "191",
            "165",
            "163",
            "185",
            "161",
            "183",
            "314",
            "313",
            "312",
            "311",
            "22",
            "32",
            "24",
            "31",
            "28",
            "21",
            "4",
            "12",
            "9",
            "153",
            "127",
            "149",
            "121",
            "143",
            "139",
            "117",
            "33",
            "298",
            "320",
            "323",
            "130",
            "131",
            "301",
            "340",
            "328",
            "302",
            "343",
            "345",
            "347",
            "348",
            "303",
            "331",
            "306",
            "107",
            "134",
            "113",
            "116",
            "122",
            "142",
            "119",
            "141",
            "145",
            "129",
            "29",
            "30",
            "15",
            "52",
            "63",
            "216",
            "239",
            "231",
            "203",
            "391",
            "363",
            "358",
            "401",
            "402",
            "229",
            "233",
            "212",
            "217",
            "242",
            "246",
            "225",
            "413",
            "371",
            "370",
            "378",
            "412",
            "373",
            "237",
            "208",
            "230",
            "227",
            "209",
            "210",
            "204",
            "205",
            "392",
            "408",
            "362",
            "390",
            "382",
            "364",
            "393",
            "367",
            "105",
            "89",
            "90",
            "247",
            "249",
            "243",
            "241",
            "213",
            "235",
            "236",
            "234",
            "214",
            "91",
            "95",
            "254",
            "379",
            "250",
            "399",
            "276",
            "262",
            "256",
            "258",
            "282",
            "296",
            "269",
            "279",
            "377",
            "416",
            "387",
            "375",
            "398",
            "415",
            "414",
            "411",
            "85",
            "88",
            "40",
            "157",
            "180",
            "178",
            "318",
            "354",
            "334",
            "47",
            "70",
            "66",
            "112",
            "137",
            "395",
            "372",
            "104",
            "102",
            "71",
            "75",
            "69",
            "400",
            "360",
            "389",
            "103",
            "1",
            "13",
            "20",
            "26",
            "16",
            "164",
            "160",
            "158",
            "170",
            "196",
            "156",
            "319",
            "353",
            "315",
            "181",
            "327",
            "336",
            "3",
            "19",
            "8",
            "43",
            "46",
            "277",
            "245",
            "407",
            "380",
            "350",
            "2",
            "136",
            "344",
            "300",
            "342",
            "308",
            "106",
            "333",
            "100",
            "278",
            "286",
            "272",
            "268",
            "274",
            "384",
            "223",
            "337",
            "357",
            "17",
            "37",
            "11",
            "14",
            "151",
            "54",
            "299",
            "324",
            "168",
            "155",
            "144",
            "147",
            "96",
            "361",
            "359",
            "365",
            "406",
            "93",
            "189",
            "36",
            "317",
            "356",
            "352",
            "60",
            "369",
            "238",
            "403",
            "405",
            "226",
            "202",
            "232",
            "310",
            "154",
            "192",
            "199",
            "198",
            "38",
            "81",
            "48",
            "255",
            "252",
            "101",
            "410",
            "388",
            "72",
            "330",
            "259",
            "281",
            "376",
            "187",
            "190",
            "186",
            "159",
            "27",
            "6",
            "383",
            "215",
            "84",
            "78",
            "45",
            "275",
            "295",
            "290",
            "59",
            "68",
            "332",
            "305",
            "42",
            "83",
            "374",
            "291",
            "404",
            "193",
            "18",
            "351",
            "82",
            "73",
            "219",
            "61",
            "94",
            "65",
            "307",
            "329",
            "346",
            "316",
            "206",
            "385",
            "218",
            "355",
            "409",
            "23",
            "108",
            "109",
            "322",
            "304",
            "133",
            "321",
            "341",
            "381",
            "98",
            "99",
            "417"
        ]
    },
    "steps": {
        "0": 1465013,
        "1": 1436918,
        "10": 1402360,
        "100": 337362,
        "1005": 240486,
        "1006": 237823,
        "1009": 237819,
        "101": 334513,
        "1013": 237814,
        "1018": 237812,
        "102": 332457,
        "1023": 237810,
        "1024": 237806,
        "1025": 237803,
        "1026": 237775,
        "1027": 237474,
        "103": 332435,
        "1034": 237473,
        "104": 331336,
        "1041": 237464,
        "1049": 237462,
        "105": 328811,
        "1051": 236954,
        "1059": 236942,
        "106": 327453,
        "1066": 236935,
        "107": 323339,
        "1074": 235547,
        "1076": 235539,
        "108": 323291,
        "1084": 235516,
        "109": 323139,
        "1091": 235515,
        "1099": 234442,
        "11": 1401666,
        "110": 322995,
        "1107": 233969,
        "111": 322984,
        "1115": 233225,
        "1116": 232980,
        "1118": 232938,
        "112": 322745,
        "1125": 232937,
        "113": 321568,
        "1132": 232728,
        "1136": 231887,
        "1137": 231875,
        "114": 319457,
        "1140": 231363,
        "1142": 231345,
        "1143": 231313,
        "1145": 231309,
        "1149": 231295,
        "115": 319353,
        "1153": 230909,
        "1157": 230905,
        "116": 319086,
        "1161": 230821,
        "1165": 230818,
        "1167": 230805,
        "117": 319083,
        "1171": 230801,
        "1179": 230784,
        "118": 318888,
        "1180": 230125,
        "1182": 230122,
        "1186": 230065,
        "119": 318857,
        "1191": 230063,
        "1196": 230062,
        "12": 1399906,
        "120": 318729,
        "1204": 230061,
        "121": 318619,
        "1211": 228787,
        "1219": 228764,
        "122": 315368,
        "1227": 228753,
        "123": 314593,
        "1236": 228716,
        "124": 314451,
        "1245": 228710,
        "1248": 228708,
        "125": 314113,
        "1257": 228695,
        "126": 312203,
        "1264": 228691,
        "127": 312191,
        "1273": 228682,
        "128": 310877,
        "1283": 228674,
        "129": 307766,
        "1291": 228664,
        "1298": 228662,
        "13": 1399724,
        "130": 306323,
        "1301": 228643,
        "1305": 228399,
        "1306": 228391,
        "1307": 228383,
        "1308": 228364,
        "131": 306160,
        "1312": 228359,
        "1316": 226274,
        "1319": 226273,
        "132": 306128,
        "1323": 226256,
        "1328": 226247,
        "133": 306121,
        "1335": 225877,
        "134": 305939,
        "1343": 223949,
        "1346": 223948,
        "1348": 223939,
        "135": 305750,
        "1350": 223930,
        "1353": 223929,
        "1355": 223927,
        "1356": 223469,
        "1358": 223053,
        "136": 305161,
        "1360": 222925,
        "1362": 222916,
        "1365": 222910,
        "1369": 222902,
        "137": 305150,
        "1373": 222894,
        "1379": 221462,
        "1386": 221447,
        "139": 305145,
        "1395": 221424,
        "1397": 221298,
        "14": 1399538,
        "1400": 221297,
        "1402": 221286,
        "1405": 221237,
        "141": 305107,
        "1410": 221232,
        "1412": 221025,
        "1418": 221024,
        "1419": 220988,
        "142": 304807,
        "1426": 220751,
        "1434": 220749,
        "144": 304795,
        "1442": 220748,
        "1452": 219924,
        "146": 304785,
        "1460": 219900,
        "1468": 219876,
        "1475": 219775,
        "148": 304777,
        "1482": 219768,
        "1490": 219756,
        "1499": 219752,
        "15": 1396733,
        "150": 304770,
        "1507": 219685,
        "151": 304735,
        "1515": 219684,
        "1524": 219680,
        "1533": 219209,
        "154": 304672,
        "1542": 219181,
        "1552": 219180,
        "156": 303805,
        "1561": 219179,
        "1568": 219168,
        "1573": 219166,
        "1577": 219147,
        "1586": 219142,
        "159": 303804,
        "1596": 219141,
        "16": 1395816,
        "1601": 219139,
        "1611": 219111,
        "162": 303801,
        "1621": 219110,
        "1631": 219089,
        "1641": 219087,
        "165": 300652,
        "1651": 219055,
        "1661": 219052,
        "1671": 219050,
        "1682": 219043,
        "169": 300506,
        "1693": 219041,
        "17": 1395318,
        "1702": 219030,
        "1709": 219025,
        "171": 298100,
        "1717": 219019,
        "1726": 219015,
        "1735": 219014,
        "1743": 219013,
        "175": 297852,
        "1753": 219011,
        "1754": 219001,
        "1763": 219000,
        "177": 297847,
        "1770": 218978,
        "1780": 218977,
        "1791": 218962,
        "18": 1395306,
        "1800": 218960,
        "181": 297315,
        "1811": 218920,
        "1822": 218915,
        "1834": 218913,
        "1847": 215784,
        "1848": 215069,
        "185": 297234,
        "1850": 214865,
        "1851": 214609,
        "1853": 213384,
        "1854": 211307,
        "1855": 211254,
        "1857": 211243,
        "1859": 209370,
        "1861": 209261,
        "1866": 207494,
        "1872": 207492,
        "1878": 207476,
        "1885": 207463,
        "189": 297233,
        "1891": 207445,
        "1898": 205784,
        "19": 1394685,
        "1900": 205676,
        "1907": 205675,
        "1910": 205631,
        "1912": 205570,
        "1917": 205563,
        "1920": 205545,
        "1926": 205498,
        "193": 297165,
        "1933": 205363,
        "1936": 205348,
        "194": 296318,
        "1942": 204640,
        "195": 295621,
        "1950": 203738,
        "1958": 203692,
        "1966": 203273,
        "1967": 203173,
        "1972": 203170,
        "1978": 203079,
        "1986": 203061,
        "199": 294427,
        "1995": 202969,
        "2": 1416229,
        "20": 1391673,
        "2003": 200507,
        "2011": 200476,
        "2015": 200224,
        "2019": 199870,
        "2025": 199827,
        "203": 294394,
        "2033": 199798,
        "2042": 199447,
        "2050": 199445,
        "2051": 199436,
        "2052": 199170,
        "2053": 196658,
        "2054": 195839,
        "2056": 194590,
        "2064": 193345,
        "2067": 193338,
        "207": 290865,
        "2075": 193175,
        "2084": 193166,
        "2093": 193118,
        "21": 1390275,
        "210": 290140,
        "2102": 193065,
        "2112": 193055,
        "2124": 192816,
        "2136": 192666,
        "215": 290080,
        "2151": 189310,
        "2153": 188101,
        "2155": 186709,
        "2158": 186464,
        "2161": 185842,
        "2163": 185517,
        "2166": 185483,
        "2170": 185481,
        "2174": 185235,
        "2178": 185193,
        "2179": 185192,
        "2180": 184148,
        "2181": 184090,
        "2183": 183673,
        "2188": 183360,
        "219": 289198,
        "2194": 183356,
        "22": 1389702,
        "2202": 183329,
        "2209": 181229,
        "2218": 181193,
        "222": 289196,
        "2221": 181090,
        "223": 289194,
        "2230": 181076,
        "2239": 180825,
        "2248": 180800,
        "225": 289122,
        "2257": 180707,
        "2267": 180683,
        "227": 287903,
        "2276": 180664,
        "2286": 179498,
        "229": 287595,
        "2296": 179493,
        "23": 1389186,
        "230": 287556,
        "2307": 179484,
        "231": 287415,
        "2318": 179481,
        "2329": 179333,
        "233": 286785,
        "2334": 178872,
        "2343": 178600,
        "2346": 176628,
        "235": 285802,
        "2360": 176331,
        "2363": 176292,
        "2366": 173505,
        "237": 284548,
        "2370": 173426,
        "2373": 173319,
        "2381": 170946,
        "2390": 170945,
        "2398": 170941,
        "24": 1385453,
        "240": 284481,
        "2407": 170859,
        "2417": 170570,
        "2427": 170554,
        "243": 284477,
        "2437": 169939,
        "2446": 169510,
        "2451": 168750,
        "246": 284476,
        "2461": 168580,
        "2462": 167899,
        "2471": 166867,
        "2473": 166785,
        "2490": 166759,
        "2491": 166757,
        "2494": 166110,
        "2499": 165878,
        "25": 1385333,
        "250": 284475,
        "2505": 165852,
        "2512": 162642,
        "2521": 162634,
        "2533": 162414,
        "254": 284345,
        "2545": 162388,
        "2546": 162215,
        "2547": 162205,
        "2548": 162204,
        "2549": 162130,
        "2551": 162123,
        "2553": 162119,
        "2555": 162112,
        "2557": 162107,
        "2559": 162082,
        "2560": 162079,
        "2563": 161865,
        "2565": 161464,
        "2567": 161454,
        "2568": 160783,
        "2571": 160713,
        "2573": 160701,
        "2575": 160511,
        "2577": 160501,
        "258": 284259,
        "2580": 160496,
        "2583": 160494,
        "2586": 160493,
        "2589": 160352,
        "259": 284256,
        "2592": 160348,
        "2596": 160346,
        "2598": 160272,
        "26": 1385166,
        "260": 284242,
        "2600": 160205,
        "2601": 159850,
        "2602": 159805,
        "2603": 158468,
        "2604": 157045,
        "2605": 157024,
        "2607": 156827,
        "2608": 156627,
        "261": 284214,
        "2610": 156624,
        "2611": 156603,
        "2613": 156567,
        "2614": 156556,
        "2616": 156550,
        "2618": 156519,
        "2620": 156506,
        "2622": 156495,
        "2625": 156493,
        "2628": 156486,
        "263": 284197,
        "2632": 156478,
        "2635": 156476,
        "2639": 156468,
        "2643": 156446,
        "2648": 156426,
        "2653": 156405,
        "2657": 156377,
        "2661": 156375,
        "2666": 156340,
        "267": 284167,
        "2671": 156327,
        "2678": 156304,
        "2685": 156240,
        "2687": 156197,
        "2688": 156060,
        "2691": 156024,
        "2693": 156023,
        "2694": 156019,
        "27": 1384944,
        "2701": 156016,
        "2708": 156003,
        "2710": 155988,
        "2711": 155975,
        "2717": 154688,
        "272": 284149,
        "2725": 154480,
        "2733": 154389,
        "2734": 154197,
        "2736": 154085,
        "2737": 153777,
        "2739": 153775,
        "2741": 153670,
        "2742": 153600,
        "2743": 153591,
        "2744": 153551,
        "2746": 153343,
        "2748": 153341,
        "2749": 153267,
        "2750": 153263,
        "2751": 153123,
        "2752": 153069,
        "2753": 153064,
        "2755": 153054,
        "2756": 153053,
        "2758": 152970,
        "2760": 152947,
        "2763": 152926,
        "2765": 152901,
        "277": 283595,
        "2771": 152867,
        "2772": 152792,
        "2779": 152548,
        "2787": 151996,
        "2789": 151961,
        "2790": 151906,
        "2791": 151886,
        "2792": 151870,
        "2795": 150469,
        "2796": 150447,
        "2797": 150444,
        "2799": 150371,
        "28": 1384863,
        "2800": 150351,
        "2801": 150336,
        "2804": 150198,
        "2805": 150185,
        "2806": 150158,
        "2807": 150144,
        "2808": 150111,
        "2815": 149933,
        "282": 283594,
        "2823": 149766,
        "283": 283589,
        "2835": 148541,
        "2836": 148493,
        "2837": 148414,
        "2838": 148364,
        "2840": 148350,
        "2842": 148214,
        "2847": 148213,
        "2852": 148204,
        "2857": 148195,
        "2864": 147962,
        "2872": 147951,
        "288": 283579,
        "2883": 147941,
        "2894": 147931,
        "29": 1384332,
        "2900": 147877,
        "2901": 147217,
        "2905": 147210,
        "2906": 147172,
        "2907": 147154,
        "2910": 147148,
        "2916": 147093,
        "2928": 145846,
        "293": 283578,
        "2936": 145504,
        "2948": 145454,
        "2960": 145406,
        "2964": 145341,
        "2970": 145330,
        "2977": 145307,
        "298": 283575,
        "2989": 145249,
        "2999": 145159,
        "3": 1414584,
        "30": 1384328,
        "3004": 145116,
        "3015": 145034,
        "3027": 145032,
        "303": 283431,
        "3041": 144891,
        "3042": 144888,
        "3060": 144864,
        "3074": 144794,
        "3076": 144786,
        "3078": 144784,
        "308": 283410,
        "3081": 144713,
        "3085": 144703,
        "3087": 144702,
        "3093": 144685,
        "3099": 144679,
        "31": 1383829,
        "3102": 144669,
        "3109": 144539,
        "311": 283399,
        "3115": 144528,
        "3122": 144514,
        "3129": 144499,
        "3139": 144490,
        "3149": 144480,
        "3159": 144400,
        "316": 282983,
        "3179": 144399,
        "3196": 144362,
        "32": 1381528,
        "320": 282958,
        "3201": 141288,
        "3209": 140493,
        "3218": 140357,
        "3229": 140319,
        "3230": 140315,
        "324": 282886,
        "3243": 140239,
        "3257": 139778,
        "3269": 138962,
        "3270": 138921,
        "3271": 138707,
        "3272": 138670,
        "3273": 138640,
        "3274": 138098,
        "3275": 138087,
        "3276": 138071,
        "3277": 138057,
        "3279": 138054,
        "3282": 138051,
        "3285": 138049,
        "3287": 138046,
        "329": 282872,
        "3290": 138040,
        "3293": 138015,
        "3295": 138005,
        "3299": 138000,
        "33": 1377393,
        "3300": 137976,
        "3304": 137974,
        "3307": 137973,
        "3311": 137948,
        "3316": 137909,
        "332": 282861,
        "3320": 137906,
        "3321": 137903,
        "3322": 137892,
        "3323": 137879,
        "3327": 137633,
        "3333": 137529,
        "3336": 137465,
        "3341": 137455,
        "3346": 137433,
        "3351": 137430,
        "3352": 137428,
        "3356": 137425,
        "3358": 137297,
        "336": 282846,
        "3362": 137188,
        "3366": 137177,
        "3370": 137172,
        "3371": 137171,
        "3375": 137169,
        "3378": 137167,
        "3382": 137106,
        "3388": 137105,
        "339": 282262,
        "3394": 137102,
        "3399": 137100,
        "34": 1377182,
        "340": 282261,
        "3405": 137016,
        "3411": 136880,
        "3417": 136874,
        "342": 282228,
        "3424": 136868,
        "3430": 136865,
        "3434": 136844,
        "3438": 136788,
        "3444": 136785,
        "345": 282189,
        "3453": 136778,
        "3461": 136774,
        "3470": 136766,
        "348": 282146,
        "3480": 136670,
        "3489": 136655,
        "3499": 136651,
        "35": 1373498,
        "350": 282089,
        "3509": 136637,
        "3519": 136635,
        "352": 282053,
        "3530": 136599,
        "354": 282041,
        "3540": 136561,
        "3550": 136550,
        "3563": 136151,
        "357": 281682,
        "3576": 136032,
        "3579": 135938,
        "3582": 135915,
        "3585": 135909,
        "3589": 135903,
        "359": 281653,
        "3594": 135864,
        "3597": 135827,
        "36": 1372629,
        "3602": 135826,
        "3608": 135784,
        "3618": 135772,
        "362": 281629,
        "3627": 135747,
        "3636": 135707,
        "364": 281615,
        "3646": 135191,
        "3656": 135111,
        "3666": 134971,
        "367": 281548,
        "3676": 134925,
        "3687": 134807,
        "369": 281530,
        "37": 1371895,
        "3700": 131993,
        "3701": 131952,
        "3702": 131620,
        "3703": 131163,
        "3705": 130984,
        "3706": 130933,
        "3707": 130925,
        "3715": 130823,
        "372": 281523,
        "3724": 130821,
        "3734": 128654,
        "374": 281489,
        "3745": 128586,
        "3757": 128577,
        "376": 281481,
        "3773": 128553,
        "3781": 128539,
        "379": 281474,
        "3790": 126046,
        "38": 1371693,
        "380": 281470,
        "3801": 125814,
        "3815": 125800,
        "3816": 124929,
        "3817": 124886,
        "3818": 124453,
        "382": 281211,
        "3827": 124430,
        "383": 281203,
        "3837": 124417,
        "385": 281184,
        "3850": 124382,
        "3851": 124370,
        "3852": 124357,
        "3854": 124339,
        "3856": 124295,
        "3858": 124261,
        "3859": 124247,
        "3862": 124238,
        "3864": 124227,
        "3868": 124216,
        "387": 279719,
        "3871": 124208,
        "3874": 124203,
        "3879": 124202,
        "388": 279570,
        "3884": 124192,
        "3887": 124188,
        "3893": 124181,
        "39": 1371389,
        "3900": 124180,
        "391": 279569,
        "3911": 124170,
        "3923": 124113,
        "3924": 124078,
        "3927": 123980,
        "3930": 123975,
        "3946": 123973,
        "395": 279566,
        "396": 279564,
        "3968": 123964,
        "398": 279508,
        "3980": 123962,
        "3982": 123960,
        "3983": 123952,
        "3987": 123561,
        "3988": 123557,
        "399": 279506,
        "3994": 123472,
        "4": 1412961,
        "40": 1368170,
        "4009": 123323,
        "4011": 123313,
        "4015": 123312,
        "4024": 123160,
        "403": 279505,
        "4040": 123147,
        "4049": 123145,
        "405": 279503,
        "4059": 123144,
        "4061": 123132,
        "4076": 122832,
        "408": 279502,
        "4089": 120947,
        "4098": 120925,
        "41": 367893,
        "411": 279500,
        "4111": 120718,
        "4112": 120526,
        "4113": 120524,
        "4115": 118574,
        "4116": 118571,
        "4118": 118557,
        "4120": 118201,
        "4122": 117607,
        "4124": 117544,
        "4126": 117377,
        "4128": 117375,
        "4132": 117363,
        "4133": 117318,
        "4136": 117317,
        "414": 279498,
        "4140": 117273,
        "4143": 117264,
        "4145": 117255,
        "4149": 117240,
        "4154": 117239,
        "4159": 117216,
        "4165": 117203,
        "418": 275588,
        "42": 364728,
        "422": 275359,
        "425": 275358,
        "428": 275151,
        "43": 364613,
        "430": 275126,
        "433": 275116,
        "434": 275098,
        "435": 275004,
        "438": 274843,
        "44": 364612,
        "442": 274183,
        "446": 274110,
        "45": 364378,
        "450": 274035,
        "454": 272829,
        "458": 272663,
        "459": 272662,
        "46": 363413,
        "462": 272594,
        "464": 272592,
        "466": 272591,
        "469": 272585,
        "47": 363347,
        "473": 272528,
        "477": 271449,
        "48": 363301,
        "482": 271362,
        "486": 271357,
        "49": 360279,
        "490": 270684,
        "494": 270588,
        "497": 270578,
        "5": 1409569,
        "50": 360275,
        "501": 270472,
        "506": 267878,
        "508": 267873,
        "51": 360263,
        "513": 267871,
        "517": 267868,
        "52": 359480,
        "522": 267867,
        "527": 267819,
        "53": 359141,
        "531": 267802,
        "536": 267785,
        "54": 359138,
        "541": 267784,
        "546": 265585,
        "55": 358516,
        "552": 265391,
        "557": 265376,
        "56": 358130,
        "562": 264785,
        "568": 263521,
        "569": 262331,
        "57": 358121,
        "575": 262307,
        "576": 262305,
        "578": 261938,
        "58": 358010,
        "584": 261785,
        "589": 261716,
        "595": 261693,
        "6": 1408694,
        "60": 357951,
        "601": 261583,
        "606": 261567,
        "61": 357728,
        "612": 261062,
        "618": 261013,
        "62": 357727,
        "623": 261007,
        "629": 260993,
        "63": 357624,
        "632": 260992,
        "638": 260951,
        "64": 357623,
        "645": 260938,
        "651": 260932,
        "653": 260921,
        "654": 260910,
        "656": 260840,
        "657": 258866,
        "658": 258843,
        "66": 357552,
        "662": 258842,
        "665": 258713,
        "668": 258670,
        "67": 357363,
        "670": 258645,
        "673": 258644,
        "675": 258585,
        "677": 258583,
        "679": 257942,
        "681": 257315,
        "683": 257303,
        "688": 257288,
        "69": 357174,
        "693": 257280,
        "696": 256610,
        "698": 256608,
        "7": 1408181,
        "70": 357005,
        "701": 256604,
        "706": 256599,
        "711": 254044,
        "716": 253959,
        "72": 356954,
        "722": 253934,
        "724": 253914,
        "726": 253863,
        "729": 253533,
        "73": 356887,
        "731": 253409,
        "734": 253408,
        "735": 253262,
        "74": 356870,
        "740": 253259,
        "742": 253254,
        "743": 253228,
        "745": 253213,
        "746": 253184,
        "75": 356799,
        "750": 253171,
        "754": 253162,
        "759": 252587,
        "76": 356767,
        "763": 252567,
        "768": 252515,
        "77": 354904,
        "772": 252340,
        "777": 252313,
        "78": 353618,
        "782": 252290,
        "783": 252287,
        "786": 252276,
        "79": 352615,
        "791": 252275,
        "794": 252272,
        "799": 252238,
        "8": 1407511,
        "80": 352518,
        "804": 251768,
        "808": 251758,
        "81": 352422,
        "814": 251722,
        "819": 251269,
        "82": 349505,
        "824": 249396,
        "828": 249372,
        "83": 348764,
        "831": 249370,
        "833": 249369,
        "835": 249368,
        "838": 249243,
        "84": 348674,
        "840": 249143,
        "843": 246784,
        "845": 246782,
        "849": 246724,
        "85": 348399,
        "853": 246678,
        "857": 246658,
        "86": 347590,
        "861": 246657,
        "864": 246610,
        "868": 246584,
        "869": 246582,
        "87": 343857,
        "872": 246559,
        "876": 246555,
        "879": 246337,
        "88": 343848,
        "882": 246243,
        "884": 246213,
        "887": 245659,
        "89": 343844,
        "890": 245646,
        "892": 244317,
        "893": 244312,
        "896": 244296,
        "897": 244293,
        "898": 244292,
        "9": 1403075,
        "90": 343621,
        "901": 244271,
        "903": 244223,
        "905": 244221,
        "907": 243772,
        "91": 343196,
        "910": 243770,
        "915": 243759,
        "92": 342680,
        "920": 243755,
        "925": 243736,
        "93": 342139,
        "931": 243725,
        "936": 243721,
        "94": 342112,
        "942": 243701,
        "944": 241943,
        "95": 340805,
        "950": 241912,
        "955": 241911,
        "96": 340476,
        "962": 241896,
        "967": 241895,
        "97": 340440,
        "973": 241888,
        "979": 241869,
        "98": 340412,
        "985": 241865,
        "99": 337702,
        "991": 241863,
        "992": 241304,
        "998": 240727
    },
    "timeout": 4170
}